{
  "disc-bellows-pump-mondo-1-5lt": {
    "prices": [
      {
        "storeId": "foleja",
        "price": null,
        "inStock": null,
        "stockLabel": "E panjohur",
        "productUrl": null,
        "lastChecked": "2026-05-02T14:31:39.958Z",
        "error": "Produkti nuk u gjet"
      },
      {
        "storeId": "shpresa",
        "price": null,
        "inStock": null,
        "stockLabel": "E panjohur",
        "productUrl": null,
        "lastChecked": "2026-05-02T14:31:41.268Z",
        "error": "Produkti nuk u gjet"
      },
      {
        "storeId": "neptun",
        "price": null,
        "inStock": null,
        "stockLabel": "E panjohur",
        "productUrl": null,
        "lastChecked": "2026-05-02T14:31:39.699Z",
        "error": "Produkti nuk u gjet"
      },
      {
        "storeId": "globe",
        "price": null,
        "inStock": null,
        "stockLabel": "E panjohur",
        "productUrl": null,
        "lastChecked": "2026-05-02T14:31:39.684Z",
        "error": "Produkti nuk u gjet"
      },
      {
        "storeId": "albagame",
        "price": null,
        "inStock": null,
        "stockLabel": "E panjohur",
        "productUrl": null,
        "lastChecked": "2026-05-02T14:31:39.714Z",
        "error": "Produkti nuk u gjet"
      }
    ],
    "refreshedAt": "2026-05-02T14:31:41.277Z"
  },
  "disc-bellows-pump-mondo-5lt": {
    "prices": [
      {
        "storeId": "foleja",
        "price": null,
        "inStock": null,
        "stockLabel": "E panjohur",
        "productUrl": null,
        "lastChecked": "2026-05-02T14:31:40.285Z",
        "error": "Produkti nuk u gjet"
      },
      {
        "storeId": "shpresa",
        "price": null,
        "inStock": null,
        "stockLabel": "E panjohur",
        "productUrl": null,
        "lastChecked": "2026-05-02T14:31:41.406Z",
        "error": "Produkti nuk u gjet"
      },
      {
        "storeId": "neptun",
        "price": null,
        "inStock": null,
        "stockLabel": "E panjohur",
        "productUrl": null,
        "lastChecked": "2026-05-02T14:31:39.727Z",
        "error": "Produkti nuk u gjet"
      },
      {
        "storeId": "globe",
        "price": null,
        "inStock": null,
        "stockLabel": "E panjohur",
        "productUrl": null,
        "lastChecked": "2026-05-02T14:31:39.685Z",
        "error": "Produkti nuk u gjet"
      },
      {
        "storeId": "albagame",
        "price": null,
        "inStock": null,
        "stockLabel": "E panjohur",
        "productUrl": null,
        "lastChecked": "2026-05-02T14:31:39.721Z",
        "error": "Produkti nuk u gjet"
      }
    ],
    "refreshedAt": "2026-05-02T14:31:41.406Z"
  },
  "disc-bellows-pump-mondo-3lt": {
    "prices": [
      {
        "storeId": "foleja",
        "price": null,
        "inStock": null,
        "stockLabel": "E panjohur",
        "productUrl": null,
        "lastChecked": "2026-05-02T14:31:40.175Z",
        "error": "Produkti nuk u gjet"
      },
      {
        "storeId": "shpresa",
        "price": null,
        "inStock": null,
        "stockLabel": "E panjohur",
        "productUrl": null,
        "lastChecked": "2026-05-02T14:31:41.741Z",
        "error": "Produkti nuk u gjet"
      },
      {
        "storeId": "neptun",
        "price": null,
        "inStock": null,
        "stockLabel": "E panjohur",
        "productUrl": null,
        "lastChecked": "2026-05-02T14:31:39.704Z",
        "error": "Produkti nuk u gjet"
      },
      {
        "storeId": "globe",
        "price": null,
        "inStock": null,
        "stockLabel": "E panjohur",
        "productUrl": null,
        "lastChecked": "2026-05-02T14:31:39.700Z",
        "error": "Produkti nuk u gjet"
      },
      {
        "storeId": "albagame",
        "price": null,
        "inStock": null,
        "stockLabel": "E panjohur",
        "productUrl": null,
        "lastChecked": "2026-05-02T14:31:39.735Z",
        "error": "Produkti nuk u gjet"
      }
    ],
    "refreshedAt": "2026-05-02T14:31:41.742Z"
  },
  "disc-fisher-price-dance-n-groove-penguin": {
    "prices": [
      {
        "storeId": "foleja",
        "price": null,
        "inStock": null,
        "stockLabel": "E panjohur",
        "productUrl": null,
        "lastChecked": "2026-05-02T14:31:40.597Z",
        "error": "Produkti nuk u gjet"
      },
      {
        "storeId": "shpresa",
        "price": null,
        "inStock": null,
        "stockLabel": "E panjohur",
        "productUrl": null,
        "lastChecked": "2026-05-02T14:31:42.052Z",
        "error": "Produkti nuk u gjet"
      },
      {
        "storeId": "neptun",
        "price": null,
        "inStock": null,
        "stockLabel": "E panjohur",
        "productUrl": null,
        "lastChecked": "2026-05-02T14:31:39.849Z",
        "error": "Produkti nuk u gjet"
      },
      {
        "storeId": "globe",
        "price": null,
        "inStock": null,
        "stockLabel": "E panjohur",
        "productUrl": null,
        "lastChecked": "2026-05-02T14:31:39.694Z",
        "error": "Produkti nuk u gjet"
      },
      {
        "storeId": "albagame",
        "price": null,
        "inStock": null,
        "stockLabel": "E panjohur",
        "productUrl": null,
        "lastChecked": "2026-05-02T14:31:39.767Z",
        "error": "Produkti nuk u gjet"
      }
    ],
    "refreshedAt": "2026-05-02T14:31:42.052Z"
  },
  "disc-plush-morphle-collectible-soft-toys": {
    "prices": [
      {
        "storeId": "foleja",
        "price": null,
        "inStock": null,
        "stockLabel": "E panjohur",
        "productUrl": null,
        "lastChecked": "2026-05-02T14:31:40.498Z",
        "error": "Produkti nuk u gjet"
      },
      {
        "storeId": "shpresa",
        "price": null,
        "inStock": null,
        "stockLabel": "E panjohur",
        "productUrl": null,
        "lastChecked": "2026-05-02T14:31:42.191Z",
        "error": "Produkti nuk u gjet"
      },
      {
        "storeId": "neptun",
        "price": null,
        "inStock": null,
        "stockLabel": "E panjohur",
        "productUrl": null,
        "lastChecked": "2026-05-02T14:31:39.791Z",
        "error": "Produkti nuk u gjet"
      },
      {
        "storeId": "globe",
        "price": null,
        "inStock": null,
        "stockLabel": "E panjohur",
        "productUrl": null,
        "lastChecked": "2026-05-02T14:31:39.683Z",
        "error": "Produkti nuk u gjet"
      },
      {
        "storeId": "albagame",
        "price": null,
        "inStock": null,
        "stockLabel": "E panjohur",
        "productUrl": null,
        "lastChecked": "2026-05-02T14:31:39.757Z",
        "error": "Produkti nuk u gjet"
      }
    ],
    "refreshedAt": "2026-05-02T14:31:42.192Z"
  },
  "disc-batterie-maxell-lr6-aa-1-5v-alkaline-blister-pack-4pcs-box-12-16376": {
    "prices": [
      {
        "storeId": "foleja",
        "price": null,
        "inStock": null,
        "stockLabel": "Në gjendje",
        "productUrl": "https://www.foleja.al/ACN-300286159/Bateri-AA-Maxell-LR6-100-cope-alkaline-e-arte-paketim-plastik",
        "lastChecked": "2026-05-02T14:31:41.048Z",
        "matchedName": "Bateri AA Maxell LR6, 100 copë, alkaline, e artë, paketim plastik",
        "storeProductId": "/ACN-300286159/Bateri-AA-Maxell-LR6-100-cope-alkaline-e-arte-paketim-plastik",
        "matchConfidence": 75,
        "error": "Produkti nuk u gjet"
      },
      {
        "storeId": "shpresa",
        "price": null,
        "inStock": null,
        "stockLabel": "E panjohur",
        "productUrl": null,
        "lastChecked": "2026-05-02T14:31:42.522Z",
        "error": "Produkti nuk u gjet"
      },
      {
        "storeId": "neptun",
        "price": null,
        "inStock": null,
        "stockLabel": "E panjohur",
        "productUrl": null,
        "lastChecked": "2026-05-02T14:31:39.912Z",
        "error": "Produkti nuk u gjet"
      },
      {
        "storeId": "globe",
        "price": null,
        "inStock": null,
        "stockLabel": "E panjohur",
        "productUrl": null,
        "lastChecked": "2026-05-02T14:31:39.689Z",
        "error": "Produkti nuk u gjet"
      },
      {
        "storeId": "albagame",
        "price": null,
        "inStock": null,
        "stockLabel": "E panjohur",
        "productUrl": null,
        "lastChecked": "2026-05-02T14:31:39.756Z",
        "error": "Produkti nuk u gjet"
      }
    ],
    "refreshedAt": "2026-05-02T14:31:42.522Z"
  },
  "disc-beach-bucket-set-mondo-disney-toy-story-4": {
    "prices": [
      {
        "storeId": "foleja",
        "price": null,
        "inStock": null,
        "stockLabel": "E panjohur",
        "productUrl": null,
        "lastChecked": "2026-05-02T14:31:40.681Z",
        "error": "Produkti nuk u gjet"
      },
      {
        "storeId": "shpresa",
        "price": null,
        "inStock": null,
        "stockLabel": "E panjohur",
        "productUrl": null,
        "lastChecked": "2026-05-02T14:31:42.556Z",
        "error": "Produkti nuk u gjet"
      },
      {
        "storeId": "neptun",
        "price": null,
        "inStock": null,
        "stockLabel": "E panjohur",
        "productUrl": null,
        "lastChecked": "2026-05-02T14:31:39.883Z",
        "error": "Produkti nuk u gjet"
      },
      {
        "storeId": "globe",
        "price": null,
        "inStock": null,
        "stockLabel": "E panjohur",
        "productUrl": null,
        "lastChecked": "2026-05-02T14:31:39.699Z",
        "error": "Produkti nuk u gjet"
      },
      {
        "storeId": "albagame",
        "price": null,
        "inStock": null,
        "stockLabel": "E panjohur",
        "productUrl": null,
        "lastChecked": "2026-05-02T14:31:39.760Z",
        "error": "Produkti nuk u gjet"
      }
    ],
    "refreshedAt": "2026-05-02T14:31:42.556Z"
  },
  "disc-figure-marvel-super-heroes-adventures-mega-mighties-captain-marvel-25cm": {
    "prices": [
      {
        "storeId": "foleja",
        "price": null,
        "inStock": null,
        "stockLabel": "E panjohur",
        "productUrl": null,
        "lastChecked": "2026-05-02T14:31:40.614Z",
        "error": "Produkti nuk u gjet"
      },
      {
        "storeId": "shpresa",
        "price": null,
        "inStock": null,
        "stockLabel": "E panjohur",
        "productUrl": null,
        "lastChecked": "2026-05-02T14:31:42.782Z",
        "error": "Produkti nuk u gjet"
      },
      {
        "storeId": "neptun",
        "price": null,
        "inStock": null,
        "stockLabel": "E panjohur",
        "productUrl": null,
        "lastChecked": "2026-05-02T14:31:39.978Z",
        "error": "Produkti nuk u gjet"
      },
      {
        "storeId": "globe",
        "price": null,
        "inStock": null,
        "stockLabel": "E panjohur",
        "productUrl": null,
        "lastChecked": "2026-05-02T14:31:39.686Z",
        "error": "Produkti nuk u gjet"
      },
      {
        "storeId": "albagame",
        "price": null,
        "inStock": null,
        "stockLabel": "E panjohur",
        "productUrl": null,
        "lastChecked": "2026-05-02T14:31:39.768Z",
        "error": "Produkti nuk u gjet"
      }
    ],
    "refreshedAt": "2026-05-02T14:31:42.783Z"
  },
  "albagame-batterie-maxell-lr6-aa-1-5v-alkaline-blister-pack-2pcs-16396": {
    "prices": [
      {
        "storeId": "foleja",
        "price": null,
        "inStock": null,
        "stockLabel": "Në gjendje",
        "productUrl": "https://www.foleja.al/ACN-300286159/Bateri-AA-Maxell-LR6-100-cope-alkaline-e-arte-paketim-plastik",
        "lastChecked": "2026-05-02T14:31:41.050Z",
        "matchedName": "Bateri AA Maxell LR6, 100 copë, alkaline, e artë, paketim plastik",
        "storeProductId": "/ACN-300286159/Bateri-AA-Maxell-LR6-100-cope-alkaline-e-arte-paketim-plastik",
        "matchConfidence": 75,
        "error": "Produkti nuk u gjet"
      },
      {
        "storeId": "shpresa",
        "price": null,
        "inStock": null,
        "stockLabel": "E panjohur",
        "productUrl": null,
        "lastChecked": "2026-05-02T14:31:42.812Z",
        "error": "Produkti nuk u gjet"
      },
      {
        "storeId": "neptun",
        "price": null,
        "inStock": null,
        "stockLabel": "E panjohur",
        "productUrl": null,
        "lastChecked": "2026-05-02T14:31:39.880Z",
        "error": "Produkti nuk u gjet"
      },
      {
        "storeId": "globe",
        "price": null,
        "inStock": null,
        "stockLabel": "E panjohur",
        "productUrl": null,
        "lastChecked": "2026-05-02T14:31:39.686Z",
        "error": "Produkti nuk u gjet"
      },
      {
        "storeId": "albagame",
        "price": null,
        "inStock": null,
        "stockLabel": "E panjohur",
        "productUrl": null,
        "lastChecked": "2026-05-02T14:31:39.793Z",
        "error": "Produkti nuk u gjet"
      }
    ],
    "refreshedAt": "2026-05-02T14:31:42.812Z"
  },
  "albagame-lego-super-mario-reznor-knockdown-expansion-set-71390": {
    "prices": [
      {
        "storeId": "foleja",
        "price": null,
        "inStock": null,
        "stockLabel": "E panjohur",
        "productUrl": null,
        "lastChecked": "2026-05-02T14:31:40.557Z",
        "error": "Produkti nuk u gjet"
      },
      {
        "storeId": "shpresa",
        "price": null,
        "inStock": null,
        "stockLabel": "E panjohur",
        "productUrl": null,
        "lastChecked": "2026-05-02T14:31:42.851Z",
        "error": "Produkti nuk u gjet"
      },
      {
        "storeId": "neptun",
        "price": null,
        "inStock": null,
        "stockLabel": "E panjohur",
        "productUrl": null,
        "lastChecked": "2026-05-02T14:31:39.839Z",
        "error": "Produkti nuk u gjet"
      },
      {
        "storeId": "globe",
        "price": null,
        "inStock": null,
        "stockLabel": "E panjohur",
        "productUrl": null,
        "lastChecked": "2026-05-02T14:31:39.683Z",
        "error": "Produkti nuk u gjet"
      },
      {
        "storeId": "albagame",
        "price": null,
        "inStock": null,
        "stockLabel": "E panjohur",
        "productUrl": null,
        "lastChecked": "2026-05-02T14:31:39.816Z",
        "error": "Produkti nuk u gjet"
      }
    ],
    "refreshedAt": "2026-05-02T14:31:42.851Z"
  },
  "disc-morph-s-egg-recent-toys": {
    "prices": [
      {
        "storeId": "foleja",
        "price": null,
        "inStock": null,
        "stockLabel": "E panjohur",
        "productUrl": null,
        "lastChecked": "2026-05-02T14:31:43.286Z",
        "error": "Produkti nuk u gjet"
      },
      {
        "storeId": "shpresa",
        "price": null,
        "inStock": null,
        "stockLabel": "E panjohur",
        "productUrl": null,
        "lastChecked": "2026-05-02T14:31:44.151Z",
        "error": "Produkti nuk u gjet"
      },
      {
        "storeId": "neptun",
        "price": null,
        "inStock": null,
        "stockLabel": "E panjohur",
        "productUrl": null,
        "lastChecked": "2026-05-02T14:31:43.288Z",
        "error": "Produkti nuk u gjet"
      },
      {
        "storeId": "globe",
        "price": null,
        "inStock": null,
        "stockLabel": "E panjohur",
        "productUrl": null,
        "lastChecked": "2026-05-02T14:31:43.313Z",
        "error": "Produkti nuk u gjet"
      },
      {
        "storeId": "albagame",
        "price": null,
        "inStock": null,
        "stockLabel": "E panjohur",
        "productUrl": null,
        "lastChecked": "2026-05-02T14:31:43.255Z",
        "error": "Produkti nuk u gjet"
      }
    ],
    "refreshedAt": "2026-05-02T14:31:44.151Z"
  },
  "disc-crystal-pyraminx-recent-toys": {
    "prices": [
      {
        "storeId": "foleja",
        "price": null,
        "inStock": null,
        "stockLabel": "E panjohur",
        "productUrl": null,
        "lastChecked": "2026-05-02T14:31:43.221Z",
        "error": "Produkti nuk u gjet"
      },
      {
        "storeId": "shpresa",
        "price": null,
        "inStock": null,
        "stockLabel": "E panjohur",
        "productUrl": null,
        "lastChecked": "2026-05-02T14:31:44.259Z",
        "error": "Produkti nuk u gjet"
      },
      {
        "storeId": "neptun",
        "price": null,
        "inStock": null,
        "stockLabel": "E panjohur",
        "productUrl": null,
        "lastChecked": "2026-05-02T14:31:43.293Z",
        "error": "Produkti nuk u gjet"
      },
      {
        "storeId": "globe",
        "price": null,
        "inStock": null,
        "stockLabel": "E panjohur",
        "productUrl": null,
        "lastChecked": "2026-05-02T14:31:43.270Z",
        "error": "Produkti nuk u gjet"
      },
      {
        "storeId": "albagame",
        "price": null,
        "inStock": null,
        "stockLabel": "E panjohur",
        "productUrl": null,
        "lastChecked": "2026-05-02T14:31:43.245Z",
        "error": "Produkti nuk u gjet"
      }
    ],
    "refreshedAt": "2026-05-02T14:31:44.259Z"
  },
  "disc-steam-explorers-marble-runners": {
    "prices": [
      {
        "storeId": "foleja",
        "price": null,
        "inStock": null,
        "stockLabel": "E panjohur",
        "productUrl": null,
        "lastChecked": "2026-05-02T14:31:43.499Z",
        "error": "Produkti nuk u gjet"
      },
      {
        "storeId": "shpresa",
        "price": null,
        "inStock": null,
        "stockLabel": "E panjohur",
        "productUrl": null,
        "lastChecked": "2026-05-02T14:31:44.515Z",
        "error": "Produkti nuk u gjet"
      },
      {
        "storeId": "neptun",
        "price": null,
        "inStock": null,
        "stockLabel": "E panjohur",
        "productUrl": null,
        "lastChecked": "2026-05-02T14:31:43.273Z",
        "error": "Produkti nuk u gjet"
      },
      {
        "storeId": "globe",
        "price": null,
        "inStock": null,
        "stockLabel": "E panjohur",
        "productUrl": null,
        "lastChecked": "2026-05-02T14:31:43.311Z",
        "error": "Produkti nuk u gjet"
      },
      {
        "storeId": "albagame",
        "price": null,
        "inStock": null,
        "stockLabel": "E panjohur",
        "productUrl": null,
        "lastChecked": "2026-05-02T14:31:43.241Z",
        "error": "Produkti nuk u gjet"
      }
    ],
    "refreshedAt": "2026-05-02T14:31:44.516Z"
  },
  "disc-ghost-cube-recent-toys": {
    "prices": [
      {
        "storeId": "foleja",
        "price": null,
        "inStock": null,
        "stockLabel": "E panjohur",
        "productUrl": null,
        "lastChecked": "2026-05-02T14:31:43.269Z",
        "error": "Produkti nuk u gjet"
      },
      {
        "storeId": "shpresa",
        "price": null,
        "inStock": null,
        "stockLabel": "E panjohur",
        "productUrl": null,
        "lastChecked": "2026-05-02T14:31:44.784Z",
        "error": "Produkti nuk u gjet"
      },
      {
        "storeId": "neptun",
        "price": null,
        "inStock": null,
        "stockLabel": "E panjohur",
        "productUrl": null,
        "lastChecked": "2026-05-02T14:31:43.293Z",
        "error": "Produkti nuk u gjet"
      },
      {
        "storeId": "globe",
        "price": null,
        "inStock": null,
        "stockLabel": "E panjohur",
        "productUrl": null,
        "lastChecked": "2026-05-02T14:31:43.270Z",
        "error": "Produkti nuk u gjet"
      },
      {
        "storeId": "albagame",
        "price": null,
        "inStock": null,
        "stockLabel": "E panjohur",
        "productUrl": null,
        "lastChecked": "2026-05-02T14:31:43.247Z",
        "error": "Produkti nuk u gjet"
      }
    ],
    "refreshedAt": "2026-05-02T14:31:44.785Z"
  },
  "albagame-batterie-maxell-lr03-aaa-alkaline-mn2400-2pcs-16457": {
    "prices": [
      {
        "storeId": "foleja",
        "price": null,
        "inStock": null,
        "stockLabel": "Në gjendje",
        "productUrl": "https://www.foleja.al/ALB-200000185/Bateri-Maxell-LR03-AAA-alkaline-10-cope-5-5",
        "lastChecked": "2026-05-02T14:31:44.358Z",
        "matchedName": "Bateri Maxell LR03 AAA, alkaline, 10 copë (5+5)",
        "storeProductId": "/ALB-200000185/Bateri-Maxell-LR03-AAA-alkaline-10-cope-5-5",
        "matchConfidence": 75,
        "error": "Produkti nuk u gjet"
      },
      {
        "storeId": "shpresa",
        "price": null,
        "inStock": null,
        "stockLabel": "E panjohur",
        "productUrl": null,
        "lastChecked": "2026-05-02T14:31:45.091Z",
        "error": "Produkti nuk u gjet"
      },
      {
        "storeId": "neptun",
        "price": null,
        "inStock": null,
        "stockLabel": "E panjohur",
        "productUrl": null,
        "lastChecked": "2026-05-02T14:31:43.417Z",
        "error": "Produkti nuk u gjet"
      },
      {
        "storeId": "globe",
        "price": null,
        "inStock": null,
        "stockLabel": "E panjohur",
        "productUrl": null,
        "lastChecked": "2026-05-02T14:31:43.312Z",
        "error": "Produkti nuk u gjet"
      },
      {
        "storeId": "albagame",
        "price": null,
        "inStock": null,
        "stockLabel": "E panjohur",
        "productUrl": null,
        "lastChecked": "2026-05-02T14:31:43.331Z",
        "error": "Produkti nuk u gjet"
      }
    ],
    "refreshedAt": "2026-05-02T14:31:45.091Z"
  },
  "albagame-batterie-maxell-lr03-aaa-1-5v-alkaline-blister-pack-4pcs-box-12-16401": {
    "prices": [
      {
        "storeId": "foleja",
        "price": null,
        "inStock": null,
        "stockLabel": "Në gjendje",
        "productUrl": "https://www.foleja.al/ALB-200000185/Bateri-Maxell-LR03-AAA-alkaline-10-cope-5-5",
        "lastChecked": "2026-05-02T14:31:44.361Z",
        "matchedName": "Bateri Maxell LR03 AAA, alkaline, 10 copë (5+5)",
        "storeProductId": "/ALB-200000185/Bateri-Maxell-LR03-AAA-alkaline-10-cope-5-5",
        "matchConfidence": 75,
        "error": "Produkti nuk u gjet"
      },
      {
        "storeId": "shpresa",
        "price": null,
        "inStock": null,
        "stockLabel": "E panjohur",
        "productUrl": null,
        "lastChecked": "2026-05-02T14:31:45.562Z",
        "error": "Produkti nuk u gjet"
      },
      {
        "storeId": "neptun",
        "price": null,
        "inStock": null,
        "stockLabel": "E panjohur",
        "productUrl": null,
        "lastChecked": "2026-05-02T14:31:43.449Z",
        "error": "Produkti nuk u gjet"
      },
      {
        "storeId": "globe",
        "price": null,
        "inStock": null,
        "stockLabel": "E panjohur",
        "productUrl": null,
        "lastChecked": "2026-05-02T14:31:43.310Z",
        "error": "Produkti nuk u gjet"
      },
      {
        "storeId": "albagame",
        "price": null,
        "inStock": null,
        "stockLabel": "E panjohur",
        "productUrl": null,
        "lastChecked": "2026-05-02T14:31:43.341Z",
        "error": "Produkti nuk u gjet"
      }
    ],
    "refreshedAt": "2026-05-02T14:31:45.563Z"
  },
  "disc-mini-figure-peppa-pig-little-buggy-asst": {
    "prices": [
      {
        "storeId": "foleja",
        "price": null,
        "inStock": null,
        "stockLabel": "E panjohur",
        "productUrl": null,
        "lastChecked": "2026-05-02T14:31:44.148Z",
        "error": "Produkti nuk u gjet"
      },
      {
        "storeId": "shpresa",
        "price": null,
        "inStock": null,
        "stockLabel": "E panjohur",
        "productUrl": null,
        "lastChecked": "2026-05-02T14:31:45.582Z",
        "error": "Produkti nuk u gjet"
      },
      {
        "storeId": "neptun",
        "price": null,
        "inStock": null,
        "stockLabel": "E panjohur",
        "productUrl": null,
        "lastChecked": "2026-05-02T14:31:43.410Z",
        "error": "Produkti nuk u gjet"
      },
      {
        "storeId": "globe",
        "price": null,
        "inStock": null,
        "stockLabel": "E panjohur",
        "productUrl": null,
        "lastChecked": "2026-05-02T14:31:43.311Z",
        "error": "Produkti nuk u gjet"
      },
      {
        "storeId": "albagame",
        "price": null,
        "inStock": null,
        "stockLabel": "E panjohur",
        "productUrl": null,
        "lastChecked": "2026-05-02T14:31:43.306Z",
        "error": "Produkti nuk u gjet"
      }
    ],
    "refreshedAt": "2026-05-02T14:31:45.582Z"
  },
  "disc-lego-star-wars-imperial-star-destroyer-75394": {
    "prices": [
      {
        "storeId": "foleja",
        "price": 23500,
        "inStock": null,
        "stockLabel": "E panjohur",
        "productUrl": "https://www.foleja.al/ACN-300172829/Set-LEGO-Star-Wars-75394-Imperial-Star-Destroyer",
        "lastChecked": "2026-05-02T14:31:43.871Z",
        "matchedName": "Set LEGO Star Wars 75394 Imperial Star Destroyer",
        "storeProductId": "/ACN-300172829/Set-LEGO-Star-Wars-75394-Imperial-Star-Destroyer",
        "matchConfidence": 100
      },
      {
        "storeId": "shpresa",
        "price": null,
        "inStock": null,
        "stockLabel": "E panjohur",
        "productUrl": null,
        "lastChecked": "2026-05-02T14:31:45.610Z",
        "error": "Produkti nuk u gjet"
      },
      {
        "storeId": "neptun",
        "price": null,
        "inStock": null,
        "stockLabel": "E panjohur",
        "productUrl": null,
        "lastChecked": "2026-05-02T14:31:43.428Z",
        "error": "Produkti nuk u gjet"
      },
      {
        "storeId": "globe",
        "price": null,
        "inStock": null,
        "stockLabel": "E panjohur",
        "productUrl": null,
        "lastChecked": "2026-05-02T14:31:43.312Z",
        "error": "Produkti nuk u gjet"
      },
      {
        "storeId": "albagame",
        "price": null,
        "inStock": null,
        "stockLabel": "E panjohur",
        "productUrl": null,
        "lastChecked": "2026-05-02T14:31:43.324Z",
        "error": "Produkti nuk u gjet"
      }
    ],
    "refreshedAt": "2026-05-02T14:31:45.611Z"
  }
}