{
  "albagame-figure-funko-pop-animation-1634-dragon-ball-gt-goku-w-kamehameha": {
    "prices": [
      {
        "storeId": "foleja",
        "price": null,
        "inStock": null,
        "stockLabel": "E panjohur",
        "productUrl": null,
        "lastChecked": "2026-05-06T09:43:50.695Z",
        "error": "Produkti nuk u gjet"
      },
      {
        "storeId": "shpresa",
        "price": null,
        "inStock": null,
        "stockLabel": "E panjohur",
        "productUrl": null,
        "lastChecked": "2026-05-06T09:43:54.387Z",
        "error": "Produkti nuk u gjet"
      },
      {
        "storeId": "neptun",
        "price": null,
        "inStock": null,
        "stockLabel": "Në gjendje",
        "productUrl": "https://www.neptun.al/categories/FIGURE-FUNKO-POP--ANIMATION:-NARUTO---KAKASHI-PL4430",
        "lastChecked": "2026-05-06T09:43:49.578Z",
        "matchedName": "FIGURE FUNKO POP! ANIMATION: NARUTO - KAKASHI",
        "storeProductId": "/categories/FIGURE-FUNKO-POP--ANIMATION:-NARUTO---KAKASHI-PL4430",
        "matchConfidence": 100,
        "error": "Produkti nuk u gjet"
      },
      {
        "storeId": "globe",
        "price": null,
        "inStock": null,
        "stockLabel": "E panjohur",
        "productUrl": null,
        "lastChecked": "2026-05-06T09:43:59.783Z",
        "error": "Produkti nuk u gjet"
      },
      {
        "storeId": "albagame",
        "price": null,
        "inStock": null,
        "stockLabel": "E panjohur",
        "productUrl": null,
        "lastChecked": "2026-05-06T09:43:49.744Z",
        "error": "Produkti nuk u gjet"
      }
    ],
    "refreshedAt": "2026-05-06T09:43:59.785Z"
  },
  "albagame-figure-funko-pop-television-1845-the-last-of-us-joel-miller": {
    "prices": [
      {
        "storeId": "foleja",
        "price": null,
        "inStock": null,
        "stockLabel": "E panjohur",
        "productUrl": null,
        "lastChecked": "2026-05-06T09:43:50.813Z",
        "error": "Produkti nuk u gjet"
      },
      {
        "storeId": "shpresa",
        "price": null,
        "inStock": null,
        "stockLabel": "E panjohur",
        "productUrl": null,
        "lastChecked": "2026-05-06T09:43:53.521Z",
        "error": "Produkti nuk u gjet"
      },
      {
        "storeId": "neptun",
        "price": null,
        "inStock": null,
        "stockLabel": "Në gjendje",
        "productUrl": "https://www.neptun.al/categories/Figure-Funko-Pop--Television-1549:-The-Addams-Fami-PL4306",
        "lastChecked": "2026-05-06T09:43:49.600Z",
        "matchedName": "Figure Funko Pop!?Television 1549: The Addams Fami",
        "storeProductId": "/categories/Figure-Funko-Pop--Television-1549:-The-Addams-Fami-PL4306",
        "matchConfidence": 100,
        "error": "Produkti nuk u gjet"
      },
      {
        "storeId": "globe",
        "price": null,
        "inStock": null,
        "stockLabel": "E panjohur",
        "productUrl": null,
        "lastChecked": "2026-05-06T09:44:00.514Z",
        "error": "Produkti nuk u gjet"
      },
      {
        "storeId": "albagame",
        "price": null,
        "inStock": null,
        "stockLabel": "E panjohur",
        "productUrl": null,
        "lastChecked": "2026-05-06T09:43:49.763Z",
        "error": "Produkti nuk u gjet"
      }
    ],
    "refreshedAt": "2026-05-06T09:44:00.515Z"
  },
  "albagame-figure-funko-pop-television-1883-one-piece-tony-tony-chopper": {
    "prices": [
      {
        "storeId": "foleja",
        "price": null,
        "inStock": null,
        "stockLabel": "E panjohur",
        "productUrl": null,
        "lastChecked": "2026-05-06T09:44:01.957Z",
        "error": "Produkti nuk u gjet"
      },
      {
        "storeId": "shpresa",
        "price": null,
        "inStock": null,
        "stockLabel": "E panjohur",
        "productUrl": null,
        "lastChecked": "2026-05-06T09:44:07.053Z",
        "error": "Produkti nuk u gjet"
      },
      {
        "storeId": "neptun",
        "price": null,
        "inStock": null,
        "stockLabel": "Në gjendje",
        "productUrl": "https://www.neptun.al/categories/Figure-Funko-Pop--Television-1549:-The-Addams-Fami-PL4306",
        "lastChecked": "2026-05-06T09:44:00.716Z",
        "matchedName": "Figure Funko Pop!?Television 1549: The Addams Fami",
        "storeProductId": "/categories/Figure-Funko-Pop--Television-1549:-The-Addams-Fami-PL4306",
        "matchConfidence": 100,
        "error": "Produkti nuk u gjet"
      },
      {
        "storeId": "globe",
        "price": null,
        "inStock": null,
        "stockLabel": "E panjohur",
        "productUrl": null,
        "lastChecked": "2026-05-06T09:44:07.376Z",
        "error": "Produkti nuk u gjet"
      },
      {
        "storeId": "albagame",
        "price": null,
        "inStock": null,
        "stockLabel": "E panjohur",
        "productUrl": null,
        "lastChecked": "2026-05-06T09:44:00.916Z",
        "error": "Produkti nuk u gjet"
      }
    ],
    "refreshedAt": "2026-05-06T09:44:07.377Z"
  },
  "albagame-figure-funko-pop-television-1880-one-piece-nami": {
    "prices": [
      {
        "storeId": "foleja",
        "price": null,
        "inStock": null,
        "stockLabel": "E panjohur",
        "productUrl": null,
        "lastChecked": "2026-05-06T09:44:01.924Z",
        "error": "Produkti nuk u gjet"
      },
      {
        "storeId": "shpresa",
        "price": null,
        "inStock": null,
        "stockLabel": "E panjohur",
        "productUrl": null,
        "lastChecked": "2026-05-06T09:44:08.845Z",
        "error": "Produkti nuk u gjet"
      },
      {
        "storeId": "neptun",
        "price": null,
        "inStock": null,
        "stockLabel": "Në gjendje",
        "productUrl": "https://www.neptun.al/categories/Figure-Funko-Pop--Television-1549:-The-Addams-Fami-PL4306",
        "lastChecked": "2026-05-06T09:44:00.728Z",
        "matchedName": "Figure Funko Pop!?Television 1549: The Addams Fami",
        "storeProductId": "/categories/Figure-Funko-Pop--Television-1549:-The-Addams-Fami-PL4306",
        "matchConfidence": 100,
        "error": "Produkti nuk u gjet"
      },
      {
        "storeId": "globe",
        "price": null,
        "inStock": null,
        "stockLabel": "E panjohur",
        "productUrl": null,
        "lastChecked": "2026-05-06T09:44:08.622Z",
        "error": "Produkti nuk u gjet"
      },
      {
        "storeId": "albagame",
        "price": null,
        "inStock": null,
        "stockLabel": "E panjohur",
        "productUrl": null,
        "lastChecked": "2026-05-06T09:44:00.918Z",
        "error": "Produkti nuk u gjet"
      }
    ],
    "refreshedAt": "2026-05-06T09:44:08.846Z"
  },
  "albagame-figure-funko-pop-animation-2058-sakamoto-days-taro-sakamoto-w-chase": {
    "prices": [
      {
        "storeId": "foleja",
        "price": null,
        "inStock": null,
        "stockLabel": "E panjohur",
        "productUrl": null,
        "lastChecked": "2026-05-06T09:44:01.986Z",
        "error": "Produkti nuk u gjet"
      },
      {
        "storeId": "shpresa",
        "price": null,
        "inStock": null,
        "stockLabel": "E panjohur",
        "productUrl": null,
        "lastChecked": "2026-05-06T09:44:08.867Z",
        "error": "Produkti nuk u gjet"
      },
      {
        "storeId": "neptun",
        "price": null,
        "inStock": null,
        "stockLabel": "Në gjendje",
        "productUrl": "https://www.neptun.al/categories/FIGURE-FUNKO-POP--ANIMATION:-NARUTO---KAKASHI-PL4430",
        "lastChecked": "2026-05-06T09:44:00.708Z",
        "matchedName": "FIGURE FUNKO POP! ANIMATION: NARUTO - KAKASHI",
        "storeProductId": "/categories/FIGURE-FUNKO-POP--ANIMATION:-NARUTO---KAKASHI-PL4430",
        "matchConfidence": 100,
        "error": "Produkti nuk u gjet"
      },
      {
        "storeId": "globe",
        "price": null,
        "inStock": null,
        "stockLabel": "E panjohur",
        "productUrl": null,
        "lastChecked": "2026-05-06T09:44:06.205Z",
        "error": "Produkti nuk u gjet"
      },
      {
        "storeId": "albagame",
        "price": null,
        "inStock": null,
        "stockLabel": "E panjohur",
        "productUrl": null,
        "lastChecked": "2026-05-06T09:44:00.913Z",
        "error": "Produkti nuk u gjet"
      }
    ],
    "refreshedAt": "2026-05-06T09:44:08.868Z"
  },
  "albagame-figure-funko-pop-television-1879-one-piece-zoro": {
    "prices": [
      {
        "storeId": "foleja",
        "price": null,
        "inStock": null,
        "stockLabel": "E panjohur",
        "productUrl": null,
        "lastChecked": "2026-05-06T09:44:01.281Z",
        "error": "Produkti nuk u gjet"
      },
      {
        "storeId": "shpresa",
        "price": null,
        "inStock": null,
        "stockLabel": "E panjohur",
        "productUrl": null,
        "lastChecked": "2026-05-06T09:44:09.205Z",
        "error": "Produkti nuk u gjet"
      },
      {
        "storeId": "neptun",
        "price": null,
        "inStock": null,
        "stockLabel": "Në gjendje",
        "productUrl": "https://www.neptun.al/categories/Figure-Funko-Pop--Television-1549:-The-Addams-Fami-PL4306",
        "lastChecked": "2026-05-06T09:44:00.712Z",
        "matchedName": "Figure Funko Pop!?Television 1549: The Addams Fami",
        "storeProductId": "/categories/Figure-Funko-Pop--Television-1549:-The-Addams-Fami-PL4306",
        "matchConfidence": 100,
        "error": "Produkti nuk u gjet"
      },
      {
        "storeId": "globe",
        "price": null,
        "inStock": null,
        "stockLabel": "E panjohur",
        "productUrl": null,
        "lastChecked": "2026-05-06T09:44:02.747Z",
        "error": "Produkti nuk u gjet"
      },
      {
        "storeId": "albagame",
        "price": null,
        "inStock": null,
        "stockLabel": "E panjohur",
        "productUrl": null,
        "lastChecked": "2026-05-06T09:44:00.934Z",
        "error": "Produkti nuk u gjet"
      }
    ],
    "refreshedAt": "2026-05-06T09:44:09.205Z"
  },
  "albagame-figure-funko-pop-animation-2259-k-pop-demon-hunters-jinu": {
    "prices": [
      {
        "storeId": "foleja",
        "price": null,
        "inStock": null,
        "stockLabel": "E panjohur",
        "productUrl": null,
        "lastChecked": "2026-05-06T09:44:01.513Z",
        "error": "Produkti nuk u gjet"
      },
      {
        "storeId": "shpresa",
        "price": null,
        "inStock": null,
        "stockLabel": "E panjohur",
        "productUrl": null,
        "lastChecked": "2026-05-06T09:44:06.860Z",
        "error": "Produkti nuk u gjet"
      },
      {
        "storeId": "neptun",
        "price": null,
        "inStock": null,
        "stockLabel": "Në gjendje",
        "productUrl": "https://www.neptun.al/categories/FIGURE-FUNKO-POP--ANIMATION:-NARUTO---KAKASHI-PL4430",
        "lastChecked": "2026-05-06T09:44:00.758Z",
        "matchedName": "FIGURE FUNKO POP! ANIMATION: NARUTO - KAKASHI",
        "storeProductId": "/categories/FIGURE-FUNKO-POP--ANIMATION:-NARUTO---KAKASHI-PL4430",
        "matchConfidence": 100,
        "error": "Produkti nuk u gjet"
      },
      {
        "storeId": "globe",
        "price": null,
        "inStock": null,
        "stockLabel": "E panjohur",
        "productUrl": null,
        "lastChecked": "2026-05-06T09:44:10.045Z",
        "error": "Produkti nuk u gjet"
      },
      {
        "storeId": "albagame",
        "price": null,
        "inStock": null,
        "stockLabel": "E panjohur",
        "productUrl": null,
        "lastChecked": "2026-05-06T09:44:00.915Z",
        "error": "Produkti nuk u gjet"
      }
    ],
    "refreshedAt": "2026-05-06T09:44:10.057Z"
  },
  "albagame-figure-funko-pop-television-1878-one-piece-monkey-d-luffy": {
    "prices": [
      {
        "storeId": "foleja",
        "price": null,
        "inStock": null,
        "stockLabel": "E panjohur",
        "productUrl": null,
        "lastChecked": "2026-05-06T09:44:01.940Z",
        "error": "Produkti nuk u gjet"
      },
      {
        "storeId": "shpresa",
        "price": null,
        "inStock": null,
        "stockLabel": "E panjohur",
        "productUrl": null,
        "lastChecked": "2026-05-06T09:44:10.072Z",
        "error": "Produkti nuk u gjet"
      },
      {
        "storeId": "neptun",
        "price": null,
        "inStock": null,
        "stockLabel": "Në gjendje",
        "productUrl": "https://www.neptun.al/categories/Figure-Funko-Pop--Television-1549:-The-Addams-Fami-PL4306",
        "lastChecked": "2026-05-06T09:44:00.732Z",
        "matchedName": "Figure Funko Pop!?Television 1549: The Addams Fami",
        "storeProductId": "/categories/Figure-Funko-Pop--Television-1549:-The-Addams-Fami-PL4306",
        "matchConfidence": 100,
        "error": "Produkti nuk u gjet"
      },
      {
        "storeId": "globe",
        "price": null,
        "inStock": null,
        "stockLabel": "E panjohur",
        "productUrl": null,
        "lastChecked": "2026-05-06T09:44:08.179Z",
        "error": "Produkti nuk u gjet"
      },
      {
        "storeId": "albagame",
        "price": null,
        "inStock": null,
        "stockLabel": "E panjohur",
        "productUrl": null,
        "lastChecked": "2026-05-06T09:44:00.909Z",
        "error": "Produkti nuk u gjet"
      }
    ],
    "refreshedAt": "2026-05-06T09:44:10.072Z"
  },
  "albagame-figure-funko-pop-animation-2233-one-piece-nico-robin": {
    "prices": [
      {
        "storeId": "foleja",
        "price": null,
        "inStock": null,
        "stockLabel": "E panjohur",
        "productUrl": null,
        "lastChecked": "2026-05-06T09:44:01.382Z",
        "error": "Produkti nuk u gjet"
      },
      {
        "storeId": "shpresa",
        "price": null,
        "inStock": null,
        "stockLabel": "E panjohur",
        "productUrl": null,
        "lastChecked": "2026-05-06T09:44:10.121Z",
        "error": "Produkti nuk u gjet"
      },
      {
        "storeId": "neptun",
        "price": null,
        "inStock": null,
        "stockLabel": "Në gjendje",
        "productUrl": "https://www.neptun.al/categories/FIGURE-FUNKO-POP--ANIMATION:-NARUTO---KAKASHI-PL4430",
        "lastChecked": "2026-05-06T09:44:00.724Z",
        "matchedName": "FIGURE FUNKO POP! ANIMATION: NARUTO - KAKASHI",
        "storeProductId": "/categories/FIGURE-FUNKO-POP--ANIMATION:-NARUTO---KAKASHI-PL4430",
        "matchConfidence": 100,
        "error": "Produkti nuk u gjet"
      },
      {
        "storeId": "globe",
        "price": null,
        "inStock": null,
        "stockLabel": "E panjohur",
        "productUrl": null,
        "lastChecked": "2026-05-06T09:44:01.083Z",
        "error": "Produkti nuk u gjet"
      },
      {
        "storeId": "albagame",
        "price": null,
        "inStock": null,
        "stockLabel": "E panjohur",
        "productUrl": null,
        "lastChecked": "2026-05-06T09:44:00.933Z",
        "error": "Produkti nuk u gjet"
      }
    ],
    "refreshedAt": "2026-05-06T09:44:10.122Z"
  },
  "albagame-figure-funko-pop-animation-2205-one-piece-ginny-w-rifle": {
    "prices": [
      {
        "storeId": "foleja",
        "price": null,
        "inStock": null,
        "stockLabel": "E panjohur",
        "productUrl": null,
        "lastChecked": "2026-05-06T09:44:01.652Z",
        "error": "Produkti nuk u gjet"
      },
      {
        "storeId": "shpresa",
        "price": null,
        "inStock": null,
        "stockLabel": "E panjohur",
        "productUrl": null,
        "lastChecked": "2026-05-06T09:44:05.603Z",
        "error": "Produkti nuk u gjet"
      },
      {
        "storeId": "neptun",
        "price": null,
        "inStock": null,
        "stockLabel": "Në gjendje",
        "productUrl": "https://www.neptun.al/categories/FIGURE-FUNKO-POP--ANIMATION:-NARUTO---KAKASHI-PL4430",
        "lastChecked": "2026-05-06T09:44:00.745Z",
        "matchedName": "FIGURE FUNKO POP! ANIMATION: NARUTO - KAKASHI",
        "storeProductId": "/categories/FIGURE-FUNKO-POP--ANIMATION:-NARUTO---KAKASHI-PL4430",
        "matchConfidence": 100,
        "error": "Produkti nuk u gjet"
      },
      {
        "storeId": "globe",
        "price": null,
        "inStock": null,
        "stockLabel": "E panjohur",
        "productUrl": null,
        "lastChecked": "2026-05-06T09:44:10.780Z",
        "error": "Produkti nuk u gjet"
      },
      {
        "storeId": "albagame",
        "price": null,
        "inStock": null,
        "stockLabel": "E panjohur",
        "productUrl": null,
        "lastChecked": "2026-05-06T09:44:00.921Z",
        "error": "Produkti nuk u gjet"
      }
    ],
    "refreshedAt": "2026-05-06T09:44:10.781Z"
  },
  "albagame-figure-funko-pop-animation-2258-k-pop-demon-hunters-mira": {
    "prices": [
      {
        "storeId": "foleja",
        "price": null,
        "inStock": null,
        "stockLabel": "E panjohur",
        "productUrl": null,
        "lastChecked": "2026-05-06T09:44:01.730Z",
        "error": "Produkti nuk u gjet"
      },
      {
        "storeId": "shpresa",
        "price": null,
        "inStock": null,
        "stockLabel": "E panjohur",
        "productUrl": null,
        "lastChecked": "2026-05-06T09:44:08.652Z",
        "error": "Produkti nuk u gjet"
      },
      {
        "storeId": "neptun",
        "price": null,
        "inStock": null,
        "stockLabel": "Në gjendje",
        "productUrl": "https://www.neptun.al/categories/FIGURE-FUNKO-POP--ANIMATION:-NARUTO---KAKASHI-PL4430",
        "lastChecked": "2026-05-06T09:44:00.754Z",
        "matchedName": "FIGURE FUNKO POP! ANIMATION: NARUTO - KAKASHI",
        "storeProductId": "/categories/FIGURE-FUNKO-POP--ANIMATION:-NARUTO---KAKASHI-PL4430",
        "matchConfidence": 100,
        "error": "Produkti nuk u gjet"
      },
      {
        "storeId": "globe",
        "price": null,
        "inStock": null,
        "stockLabel": "E panjohur",
        "productUrl": null,
        "lastChecked": "2026-05-06T09:44:11.119Z",
        "error": "Produkti nuk u gjet"
      },
      {
        "storeId": "albagame",
        "price": null,
        "inStock": null,
        "stockLabel": "E panjohur",
        "productUrl": null,
        "lastChecked": "2026-05-06T09:44:00.912Z",
        "error": "Produkti nuk u gjet"
      }
    ],
    "refreshedAt": "2026-05-06T09:44:11.132Z"
  },
  "albagame-figure-funko-pop-television-1881-one-piece-sanji": {
    "prices": [
      {
        "storeId": "foleja",
        "price": null,
        "inStock": null,
        "stockLabel": "E panjohur",
        "productUrl": null,
        "lastChecked": "2026-05-06T09:44:01.495Z",
        "error": "Produkti nuk u gjet"
      },
      {
        "storeId": "shpresa",
        "price": null,
        "inStock": null,
        "stockLabel": "E panjohur",
        "productUrl": null,
        "lastChecked": "2026-05-06T09:44:12.102Z",
        "error": "Produkti nuk u gjet"
      },
      {
        "storeId": "neptun",
        "price": null,
        "inStock": null,
        "stockLabel": "Në gjendje",
        "productUrl": "https://www.neptun.al/categories/Figure-Funko-Pop--Television-1549:-The-Addams-Fami-PL4306",
        "lastChecked": "2026-05-06T09:44:00.721Z",
        "matchedName": "Figure Funko Pop!?Television 1549: The Addams Fami",
        "storeProductId": "/categories/Figure-Funko-Pop--Television-1549:-The-Addams-Fami-PL4306",
        "matchConfidence": 100,
        "error": "Produkti nuk u gjet"
      },
      {
        "storeId": "globe",
        "price": null,
        "inStock": null,
        "stockLabel": "E panjohur",
        "productUrl": null,
        "lastChecked": "2026-05-06T09:44:08.842Z",
        "error": "Produkti nuk u gjet"
      },
      {
        "storeId": "albagame",
        "price": null,
        "inStock": null,
        "stockLabel": "E panjohur",
        "productUrl": null,
        "lastChecked": "2026-05-06T09:44:00.907Z",
        "error": "Produkti nuk u gjet"
      }
    ],
    "refreshedAt": "2026-05-06T09:44:12.103Z"
  },
  "albagame-figure-funko-pop-animation-2256-k-pop-demon-hunters-zoey": {
    "prices": [
      {
        "storeId": "foleja",
        "price": null,
        "inStock": null,
        "stockLabel": "E panjohur",
        "productUrl": null,
        "lastChecked": "2026-05-06T09:44:01.396Z",
        "error": "Produkti nuk u gjet"
      },
      {
        "storeId": "shpresa",
        "price": null,
        "inStock": null,
        "stockLabel": "E panjohur",
        "productUrl": null,
        "lastChecked": "2026-05-06T09:44:06.978Z",
        "error": "Produkti nuk u gjet"
      },
      {
        "storeId": "neptun",
        "price": null,
        "inStock": null,
        "stockLabel": "Në gjendje",
        "productUrl": "https://www.neptun.al/categories/FIGURE-FUNKO-POP--ANIMATION:-NARUTO---KAKASHI-PL4430",
        "lastChecked": "2026-05-06T09:44:00.750Z",
        "matchedName": "FIGURE FUNKO POP! ANIMATION: NARUTO - KAKASHI",
        "storeProductId": "/categories/FIGURE-FUNKO-POP--ANIMATION:-NARUTO---KAKASHI-PL4430",
        "matchConfidence": 100,
        "error": "Produkti nuk u gjet"
      },
      {
        "storeId": "globe",
        "price": null,
        "inStock": null,
        "stockLabel": "E panjohur",
        "productUrl": null,
        "lastChecked": "2026-05-06T09:44:12.223Z",
        "error": "Produkti nuk u gjet"
      },
      {
        "storeId": "albagame",
        "price": null,
        "inStock": null,
        "stockLabel": "E panjohur",
        "productUrl": null,
        "lastChecked": "2026-05-06T09:44:00.920Z",
        "error": "Produkti nuk u gjet"
      }
    ],
    "refreshedAt": "2026-05-06T09:44:12.326Z"
  },
  "albagame-figure-funko-pop-animation-2255-one-piece-jewelry-bonney-w-chase": {
    "prices": [
      {
        "storeId": "foleja",
        "price": null,
        "inStock": null,
        "stockLabel": "E panjohur",
        "productUrl": null,
        "lastChecked": "2026-05-06T09:44:01.972Z",
        "error": "Produkti nuk u gjet"
      },
      {
        "storeId": "shpresa",
        "price": null,
        "inStock": null,
        "stockLabel": "E panjohur",
        "productUrl": null,
        "lastChecked": "2026-05-06T09:44:12.327Z",
        "error": "Produkti nuk u gjet"
      },
      {
        "storeId": "neptun",
        "price": null,
        "inStock": null,
        "stockLabel": "Në gjendje",
        "productUrl": "https://www.neptun.al/categories/FIGURE-FUNKO-POP--ANIMATION:-NARUTO---KAKASHI-PL4430",
        "lastChecked": "2026-05-06T09:44:00.736Z",
        "matchedName": "FIGURE FUNKO POP! ANIMATION: NARUTO - KAKASHI",
        "storeProductId": "/categories/FIGURE-FUNKO-POP--ANIMATION:-NARUTO---KAKASHI-PL4430",
        "matchConfidence": 100,
        "error": "Produkti nuk u gjet"
      },
      {
        "storeId": "globe",
        "price": null,
        "inStock": null,
        "stockLabel": "E panjohur",
        "productUrl": null,
        "lastChecked": "2026-05-06T09:44:12.324Z",
        "error": "Produkti nuk u gjet"
      },
      {
        "storeId": "albagame",
        "price": null,
        "inStock": null,
        "stockLabel": "E panjohur",
        "productUrl": null,
        "lastChecked": "2026-05-06T09:44:00.917Z",
        "error": "Produkti nuk u gjet"
      }
    ],
    "refreshedAt": "2026-05-06T09:44:12.327Z"
  },
  "albagame-vehicle-bburago-f1-ferrari-sf-23-w-leclerc-1-24": {
    "prices": [
      {
        "storeId": "foleja",
        "price": null,
        "inStock": null,
        "stockLabel": "E panjohur",
        "productUrl": null,
        "lastChecked": "2026-05-06T09:44:13.338Z",
        "error": "Produkti nuk u gjet"
      },
      {
        "storeId": "shpresa",
        "price": null,
        "inStock": null,
        "stockLabel": "E panjohur",
        "productUrl": null,
        "lastChecked": "2026-05-06T09:44:16.246Z",
        "error": "Produkti nuk u gjet"
      },
      {
        "storeId": "neptun",
        "price": null,
        "inStock": null,
        "stockLabel": "E panjohur",
        "productUrl": null,
        "lastChecked": "2026-05-06T09:44:12.993Z",
        "error": "Produkti nuk u gjet"
      },
      {
        "storeId": "globe",
        "price": null,
        "inStock": null,
        "stockLabel": "E panjohur",
        "productUrl": null,
        "lastChecked": "2026-05-06T09:44:14.251Z",
        "error": "Produkti nuk u gjet"
      },
      {
        "storeId": "albagame",
        "price": null,
        "inStock": null,
        "stockLabel": "E panjohur",
        "productUrl": null,
        "lastChecked": "2026-05-06T09:44:12.712Z",
        "error": "Produkti nuk u gjet"
      }
    ],
    "refreshedAt": "2026-05-06T09:44:16.247Z"
  },
  "albagame-vehicle-bburago-f1-red-bull-racing-rb19-2023-w-verstappen-1-24": {
    "prices": [
      {
        "storeId": "foleja",
        "price": null,
        "inStock": null,
        "stockLabel": "E panjohur",
        "productUrl": null,
        "lastChecked": "2026-05-06T09:44:13.712Z",
        "error": "Produkti nuk u gjet"
      },
      {
        "storeId": "shpresa",
        "price": null,
        "inStock": null,
        "stockLabel": "E panjohur",
        "productUrl": null,
        "lastChecked": "2026-05-06T09:44:17.136Z",
        "error": "Produkti nuk u gjet"
      },
      {
        "storeId": "neptun",
        "price": null,
        "inStock": null,
        "stockLabel": "E panjohur",
        "productUrl": null,
        "lastChecked": "2026-05-06T09:44:12.975Z",
        "error": "Produkti nuk u gjet"
      },
      {
        "storeId": "globe",
        "price": null,
        "inStock": null,
        "stockLabel": "E panjohur",
        "productUrl": null,
        "lastChecked": "2026-05-06T09:44:17.691Z",
        "error": "Produkti nuk u gjet"
      },
      {
        "storeId": "albagame",
        "price": null,
        "inStock": null,
        "stockLabel": "E panjohur",
        "productUrl": null,
        "lastChecked": "2026-05-06T09:44:12.707Z",
        "error": "Produkti nuk u gjet"
      }
    ],
    "refreshedAt": "2026-05-06T09:44:17.728Z"
  },
  "albagame-figure-funko-pop-animation-2260-k-pop-demon-hunters-derpy-w-sussie-glow": {
    "prices": [
      {
        "storeId": "foleja",
        "price": null,
        "inStock": null,
        "stockLabel": "E panjohur",
        "productUrl": null,
        "lastChecked": "2026-05-06T09:44:13.370Z",
        "error": "Produkti nuk u gjet"
      },
      {
        "storeId": "shpresa",
        "price": null,
        "inStock": null,
        "stockLabel": "E panjohur",
        "productUrl": null,
        "lastChecked": "2026-05-06T09:44:16.003Z",
        "error": "Produkti nuk u gjet"
      },
      {
        "storeId": "neptun",
        "price": null,
        "inStock": null,
        "stockLabel": "Në gjendje",
        "productUrl": "https://www.neptun.al/categories/FIGURE-FUNKO-POP--ANIMATION:-NARUTO---KAKASHI-PL4430",
        "lastChecked": "2026-05-06T09:44:12.532Z",
        "matchedName": "FIGURE FUNKO POP! ANIMATION: NARUTO - KAKASHI",
        "storeProductId": "/categories/FIGURE-FUNKO-POP--ANIMATION:-NARUTO---KAKASHI-PL4430",
        "matchConfidence": 100,
        "error": "Produkti nuk u gjet"
      },
      {
        "storeId": "globe",
        "price": null,
        "inStock": null,
        "stockLabel": "E panjohur",
        "productUrl": null,
        "lastChecked": "2026-05-06T09:44:18.224Z",
        "error": "Produkti nuk u gjet"
      },
      {
        "storeId": "albagame",
        "price": null,
        "inStock": null,
        "stockLabel": "E panjohur",
        "productUrl": null,
        "lastChecked": "2026-05-06T09:44:12.719Z",
        "error": "Produkti nuk u gjet"
      }
    ],
    "refreshedAt": "2026-05-06T09:44:18.225Z"
  },
  "albagame-figure-funko-pop-animation-2266-jojos-bizarre-adventure-joseph-joestar": {
    "prices": [
      {
        "storeId": "foleja",
        "price": null,
        "inStock": null,
        "stockLabel": "E panjohur",
        "productUrl": null,
        "lastChecked": "2026-05-06T09:44:13.655Z",
        "error": "Produkti nuk u gjet"
      },
      {
        "storeId": "shpresa",
        "price": null,
        "inStock": null,
        "stockLabel": "E panjohur",
        "productUrl": null,
        "lastChecked": "2026-05-06T09:44:18.410Z",
        "error": "Produkti nuk u gjet"
      },
      {
        "storeId": "neptun",
        "price": null,
        "inStock": null,
        "stockLabel": "Në gjendje",
        "productUrl": "https://www.neptun.al/categories/FIGURE-FUNKO-POP--ANIMATION:-NARUTO---KAKASHI-PL4430",
        "lastChecked": "2026-05-06T09:44:12.528Z",
        "matchedName": "FIGURE FUNKO POP! ANIMATION: NARUTO - KAKASHI",
        "storeProductId": "/categories/FIGURE-FUNKO-POP--ANIMATION:-NARUTO---KAKASHI-PL4430",
        "matchConfidence": 100,
        "error": "Produkti nuk u gjet"
      },
      {
        "storeId": "globe",
        "price": null,
        "inStock": null,
        "stockLabel": "E panjohur",
        "productUrl": null,
        "lastChecked": "2026-05-06T09:44:13.892Z",
        "error": "Produkti nuk u gjet"
      },
      {
        "storeId": "albagame",
        "price": null,
        "inStock": null,
        "stockLabel": "E panjohur",
        "productUrl": null,
        "lastChecked": "2026-05-06T09:44:12.702Z",
        "error": "Produkti nuk u gjet"
      }
    ],
    "refreshedAt": "2026-05-06T09:44:18.411Z"
  },
  "albagame-figure-funko-pop-barcellona-lamine-yamal-kneeling": {
    "prices": [
      {
        "storeId": "foleja",
        "price": null,
        "inStock": null,
        "stockLabel": "E panjohur",
        "productUrl": null,
        "lastChecked": "2026-05-06T09:44:13.669Z",
        "error": "Produkti nuk u gjet"
      },
      {
        "storeId": "shpresa",
        "price": null,
        "inStock": null,
        "stockLabel": "E panjohur",
        "productUrl": null,
        "lastChecked": "2026-05-06T09:44:19.848Z",
        "error": "Produkti nuk u gjet"
      },
      {
        "storeId": "neptun",
        "price": null,
        "inStock": null,
        "stockLabel": "E panjohur",
        "productUrl": null,
        "lastChecked": "2026-05-06T09:44:12.976Z",
        "error": "Produkti nuk u gjet"
      },
      {
        "storeId": "globe",
        "price": null,
        "inStock": null,
        "stockLabel": "E panjohur",
        "productUrl": null,
        "lastChecked": "2026-05-06T09:44:20.069Z",
        "error": "Produkti nuk u gjet"
      },
      {
        "storeId": "albagame",
        "price": null,
        "inStock": null,
        "stockLabel": "E panjohur",
        "productUrl": null,
        "lastChecked": "2026-05-06T09:44:12.700Z",
        "error": "Produkti nuk u gjet"
      }
    ],
    "refreshedAt": "2026-05-06T09:44:20.071Z"
  },
  "albagame-vehicle-bburago-f1-red-bull-racing-rb20-2024-w-verstappen-1-24": {
    "prices": [
      {
        "storeId": "foleja",
        "price": null,
        "inStock": null,
        "stockLabel": "E panjohur",
        "productUrl": null,
        "lastChecked": "2026-05-06T09:44:13.698Z",
        "error": "Produkti nuk u gjet"
      },
      {
        "storeId": "shpresa",
        "price": null,
        "inStock": null,
        "stockLabel": "E panjohur",
        "productUrl": null,
        "lastChecked": "2026-05-06T09:44:20.424Z",
        "error": "Produkti nuk u gjet"
      },
      {
        "storeId": "neptun",
        "price": null,
        "inStock": null,
        "stockLabel": "E panjohur",
        "productUrl": null,
        "lastChecked": "2026-05-06T09:44:13.083Z",
        "error": "Produkti nuk u gjet"
      },
      {
        "storeId": "globe",
        "price": null,
        "inStock": null,
        "stockLabel": "E panjohur",
        "productUrl": null,
        "lastChecked": "2026-05-06T09:44:19.270Z",
        "error": "Produkti nuk u gjet"
      },
      {
        "storeId": "albagame",
        "price": null,
        "inStock": null,
        "stockLabel": "E panjohur",
        "productUrl": null,
        "lastChecked": "2026-05-06T09:44:12.705Z",
        "error": "Produkti nuk u gjet"
      }
    ],
    "refreshedAt": "2026-05-06T09:44:20.425Z"
  },
  "albagame-vehicle-bburago-f1-mercedes-w14-e-performance-2023-w-hamilton-1-24": {
    "prices": [
      {
        "storeId": "foleja",
        "price": null,
        "inStock": null,
        "stockLabel": "E panjohur",
        "productUrl": null,
        "lastChecked": "2026-05-06T09:44:13.986Z",
        "error": "Produkti nuk u gjet"
      },
      {
        "storeId": "shpresa",
        "price": null,
        "inStock": null,
        "stockLabel": "E panjohur",
        "productUrl": null,
        "lastChecked": "2026-05-06T09:44:20.636Z",
        "error": "Produkti nuk u gjet"
      },
      {
        "storeId": "neptun",
        "price": null,
        "inStock": null,
        "stockLabel": "E panjohur",
        "productUrl": null,
        "lastChecked": "2026-05-06T09:44:13.083Z",
        "error": "Produkti nuk u gjet"
      },
      {
        "storeId": "globe",
        "price": null,
        "inStock": null,
        "stockLabel": "E panjohur",
        "productUrl": null,
        "lastChecked": "2026-05-06T09:44:17.065Z",
        "error": "Produkti nuk u gjet"
      },
      {
        "storeId": "albagame",
        "price": null,
        "inStock": null,
        "stockLabel": "E panjohur",
        "productUrl": null,
        "lastChecked": "2026-05-06T09:44:12.715Z",
        "error": "Produkti nuk u gjet"
      }
    ],
    "refreshedAt": "2026-05-06T09:44:20.637Z"
  },
  "albagame-vehicle-bburago-f1-mc-laren-mcl38-2024-w-norris-scala-1-24": {
    "prices": [
      {
        "storeId": "foleja",
        "price": null,
        "inStock": null,
        "stockLabel": "E panjohur",
        "productUrl": null,
        "lastChecked": "2026-05-06T09:44:13.683Z",
        "error": "Produkti nuk u gjet"
      },
      {
        "storeId": "shpresa",
        "price": null,
        "inStock": null,
        "stockLabel": "E panjohur",
        "productUrl": null,
        "lastChecked": "2026-05-06T09:44:21.294Z",
        "error": "Produkti nuk u gjet"
      },
      {
        "storeId": "neptun",
        "price": null,
        "inStock": null,
        "stockLabel": "E panjohur",
        "productUrl": null,
        "lastChecked": "2026-05-06T09:44:12.976Z",
        "error": "Produkti nuk u gjet"
      },
      {
        "storeId": "globe",
        "price": null,
        "inStock": null,
        "stockLabel": "E panjohur",
        "productUrl": null,
        "lastChecked": "2026-05-06T09:44:20.795Z",
        "error": "Produkti nuk u gjet"
      },
      {
        "storeId": "albagame",
        "price": null,
        "inStock": null,
        "stockLabel": "E panjohur",
        "productUrl": null,
        "lastChecked": "2026-05-06T09:44:12.706Z",
        "error": "Produkti nuk u gjet"
      }
    ],
    "refreshedAt": "2026-05-06T09:44:21.295Z"
  },
  "albagame-blanket-marvel-spider-man-comics": {
    "prices": [
      {
        "storeId": "foleja",
        "price": null,
        "inStock": null,
        "stockLabel": "E panjohur",
        "productUrl": null,
        "lastChecked": "2026-05-06T09:44:13.236Z",
        "error": "Produkti nuk u gjet"
      },
      {
        "storeId": "shpresa",
        "price": null,
        "inStock": null,
        "stockLabel": "E panjohur",
        "productUrl": null,
        "lastChecked": "2026-05-06T09:44:15.474Z",
        "error": "Produkti nuk u gjet"
      },
      {
        "storeId": "neptun",
        "price": null,
        "inStock": null,
        "stockLabel": "E panjohur",
        "productUrl": null,
        "lastChecked": "2026-05-06T09:44:12.775Z",
        "error": "Produkti nuk u gjet"
      },
      {
        "storeId": "globe",
        "price": null,
        "inStock": null,
        "stockLabel": "E panjohur",
        "productUrl": null,
        "lastChecked": "2026-05-06T09:44:22.179Z",
        "error": "Produkti nuk u gjet"
      },
      {
        "storeId": "albagame",
        "price": null,
        "inStock": null,
        "stockLabel": "E panjohur",
        "productUrl": null,
        "lastChecked": "2026-05-06T09:44:12.710Z",
        "error": "Produkti nuk u gjet"
      }
    ],
    "refreshedAt": "2026-05-06T09:44:22.181Z"
  },
  "albagame-vehicle-bburago-f1-aston-martin-amr-25-2025-w-alonso-1-24": {
    "prices": [
      {
        "storeId": "foleja",
        "price": null,
        "inStock": null,
        "stockLabel": "E panjohur",
        "productUrl": null,
        "lastChecked": "2026-05-06T09:44:13.635Z",
        "error": "Produkti nuk u gjet"
      },
      {
        "storeId": "shpresa",
        "price": null,
        "inStock": null,
        "stockLabel": "E panjohur",
        "productUrl": null,
        "lastChecked": "2026-05-06T09:44:17.087Z",
        "error": "Produkti nuk u gjet"
      },
      {
        "storeId": "neptun",
        "price": null,
        "inStock": null,
        "stockLabel": "E panjohur",
        "productUrl": null,
        "lastChecked": "2026-05-06T09:44:13.120Z",
        "error": "Produkti nuk u gjet"
      },
      {
        "storeId": "globe",
        "price": null,
        "inStock": null,
        "stockLabel": "E panjohur",
        "productUrl": null,
        "lastChecked": "2026-05-06T09:44:22.719Z",
        "error": "Produkti nuk u gjet"
      },
      {
        "storeId": "albagame",
        "price": null,
        "inStock": null,
        "stockLabel": "E panjohur",
        "productUrl": null,
        "lastChecked": "2026-05-06T09:44:12.711Z",
        "error": "Produkti nuk u gjet"
      }
    ],
    "refreshedAt": "2026-05-06T09:44:22.721Z"
  },
  "albagame-blanket-pokemon-classic": {
    "prices": [
      {
        "storeId": "foleja",
        "price": null,
        "inStock": null,
        "stockLabel": "E panjohur",
        "productUrl": null,
        "lastChecked": "2026-05-06T09:44:13.180Z",
        "error": "Produkti nuk u gjet"
      },
      {
        "storeId": "shpresa",
        "price": null,
        "inStock": null,
        "stockLabel": "E panjohur",
        "productUrl": null,
        "lastChecked": "2026-05-06T09:44:14.324Z",
        "error": "Produkti nuk u gjet"
      },
      {
        "storeId": "neptun",
        "price": null,
        "inStock": null,
        "stockLabel": "E panjohur",
        "productUrl": null,
        "lastChecked": "2026-05-06T09:44:12.768Z",
        "error": "Produkti nuk u gjet"
      },
      {
        "storeId": "globe",
        "price": null,
        "inStock": null,
        "stockLabel": "E panjohur",
        "productUrl": null,
        "lastChecked": "2026-05-06T09:44:23.480Z",
        "error": "Produkti nuk u gjet"
      },
      {
        "storeId": "albagame",
        "price": null,
        "inStock": null,
        "stockLabel": "E panjohur",
        "productUrl": null,
        "lastChecked": "2026-05-06T09:44:12.672Z",
        "error": "Produkti nuk u gjet"
      }
    ],
    "refreshedAt": "2026-05-06T09:44:23.487Z"
  },
  "albagame-blanket-friends": {
    "prices": [
      {
        "storeId": "foleja",
        "price": null,
        "inStock": null,
        "stockLabel": "E panjohur",
        "productUrl": null,
        "lastChecked": "2026-05-06T09:44:12.992Z",
        "error": "Produkti nuk u gjet"
      },
      {
        "storeId": "shpresa",
        "price": null,
        "inStock": null,
        "stockLabel": "E panjohur",
        "productUrl": null,
        "lastChecked": "2026-05-06T09:44:15.191Z",
        "error": "Produkti nuk u gjet"
      },
      {
        "storeId": "neptun",
        "price": null,
        "inStock": null,
        "stockLabel": "E panjohur",
        "productUrl": null,
        "lastChecked": "2026-05-06T09:44:12.698Z",
        "error": "Produkti nuk u gjet"
      },
      {
        "storeId": "globe",
        "price": null,
        "inStock": null,
        "stockLabel": "E panjohur",
        "productUrl": null,
        "lastChecked": "2026-05-06T09:44:24.135Z",
        "error": "Produkti nuk u gjet"
      },
      {
        "storeId": "albagame",
        "price": null,
        "inStock": null,
        "stockLabel": "E panjohur",
        "productUrl": null,
        "lastChecked": "2026-05-06T09:44:12.678Z",
        "error": "Produkti nuk u gjet"
      }
    ],
    "refreshedAt": "2026-05-06T09:44:24.137Z"
  },
  "albagame-blanket-pokemon-pikachu-130x180cm": {
    "prices": [
      {
        "storeId": "foleja",
        "price": null,
        "inStock": null,
        "stockLabel": "E panjohur",
        "productUrl": null,
        "lastChecked": "2026-05-06T09:44:25.353Z",
        "error": "Produkti nuk u gjet"
      },
      {
        "storeId": "shpresa",
        "price": null,
        "inStock": null,
        "stockLabel": "E panjohur",
        "productUrl": null,
        "lastChecked": "2026-05-06T09:44:25.655Z",
        "error": "Produkti nuk u gjet"
      },
      {
        "storeId": "neptun",
        "price": null,
        "inStock": null,
        "stockLabel": "E panjohur",
        "productUrl": null,
        "lastChecked": "2026-05-06T09:44:24.715Z",
        "error": "Produkti nuk u gjet"
      },
      {
        "storeId": "globe",
        "price": null,
        "inStock": null,
        "stockLabel": "E panjohur",
        "productUrl": null,
        "lastChecked": "2026-05-06T09:44:26.629Z",
        "error": "Produkti nuk u gjet"
      },
      {
        "storeId": "albagame",
        "price": null,
        "inStock": null,
        "stockLabel": "E panjohur",
        "productUrl": null,
        "lastChecked": "2026-05-06T09:44:24.657Z",
        "error": "Produkti nuk u gjet"
      }
    ],
    "refreshedAt": "2026-05-06T09:44:26.672Z"
  },
  "albagame-lego-speed-champions-audi-revolut-f1-team-r26-race-car-77259": {
    "prices": [
      {
        "storeId": "foleja",
        "price": null,
        "inStock": null,
        "stockLabel": "E panjohur",
        "productUrl": null,
        "lastChecked": "2026-05-06T09:44:25.715Z",
        "error": "Produkti nuk u gjet"
      },
      {
        "storeId": "shpresa",
        "price": null,
        "inStock": null,
        "stockLabel": "E panjohur",
        "productUrl": null,
        "lastChecked": "2026-05-06T09:44:29.270Z",
        "error": "Produkti nuk u gjet"
      },
      {
        "storeId": "neptun",
        "price": null,
        "inStock": null,
        "stockLabel": "E panjohur",
        "productUrl": null,
        "lastChecked": "2026-05-06T09:44:24.946Z",
        "error": "Produkti nuk u gjet"
      },
      {
        "storeId": "globe",
        "price": null,
        "inStock": null,
        "stockLabel": "E panjohur",
        "productUrl": null,
        "lastChecked": "2026-05-06T09:44:29.224Z",
        "error": "Produkti nuk u gjet"
      },
      {
        "storeId": "albagame",
        "price": null,
        "inStock": null,
        "stockLabel": "E panjohur",
        "productUrl": null,
        "lastChecked": "2026-05-06T09:44:24.666Z",
        "error": "Produkti nuk u gjet"
      }
    ],
    "refreshedAt": "2026-05-06T09:44:29.270Z"
  },
  "albagame-lego-dc-comics-the-batman-batmobile-76332": {
    "prices": [
      {
        "storeId": "foleja",
        "price": null,
        "inStock": null,
        "stockLabel": "E panjohur",
        "productUrl": null,
        "lastChecked": "2026-05-06T09:44:25.701Z",
        "error": "Produkti nuk u gjet"
      },
      {
        "storeId": "shpresa",
        "price": null,
        "inStock": null,
        "stockLabel": "E panjohur",
        "productUrl": null,
        "lastChecked": "2026-05-06T09:44:30.007Z",
        "error": "Produkti nuk u gjet"
      },
      {
        "storeId": "neptun",
        "price": null,
        "inStock": null,
        "stockLabel": "E panjohur",
        "productUrl": null,
        "lastChecked": "2026-05-06T09:44:24.814Z",
        "error": "Produkti nuk u gjet"
      },
      {
        "storeId": "globe",
        "price": null,
        "inStock": null,
        "stockLabel": "E panjohur",
        "productUrl": null,
        "lastChecked": "2026-05-06T09:44:28.530Z",
        "error": "Produkti nuk u gjet"
      },
      {
        "storeId": "albagame",
        "price": null,
        "inStock": null,
        "stockLabel": "E panjohur",
        "productUrl": null,
        "lastChecked": "2026-05-06T09:44:24.664Z",
        "error": "Produkti nuk u gjet"
      }
    ],
    "refreshedAt": "2026-05-06T09:44:30.008Z"
  },
  "albagame-lego-marvel-iron-man-mark-3-collectors-edition-76344": {
    "prices": [
      {
        "storeId": "foleja",
        "price": null,
        "inStock": null,
        "stockLabel": "Në gjendje",
        "productUrl": "https://www.foleja.al/ACN-300264664/Set-LEGO-Marvel-Iron-Man-MK4-Bust-76327-me-minifigure-per-te-rritur-Kuqe",
        "lastChecked": "2026-05-06T09:44:25.812Z",
        "matchedName": "Set LEGO Marvel Iron Man MK4 Bust 76327, me minifigurë, për të rritur, Kuqe",
        "storeProductId": "/ACN-300264664/Set-LEGO-Marvel-Iron-Man-MK4-Bust-76327-me-minifigure-per-te-rritur-Kuqe",
        "matchConfidence": 100,
        "error": "Produkti nuk u gjet"
      },
      {
        "storeId": "shpresa",
        "price": null,
        "inStock": null,
        "stockLabel": "E panjohur",
        "productUrl": null,
        "lastChecked": "2026-05-06T09:44:28.791Z",
        "error": "Produkti nuk u gjet"
      },
      {
        "storeId": "neptun",
        "price": null,
        "inStock": null,
        "stockLabel": "Në gjendje",
        "productUrl": "https://www.neptun.al/categories/LEGO-IRON-MAN---IRON-LEGION-VS--HYDRA-76288-PL4582",
        "lastChecked": "2026-05-06T09:44:24.343Z",
        "matchedName": "LEGO MARVEL IRON MAN & IRON LEGION VS. HYDRA 76288",
        "storeProductId": "/categories/LEGO-IRON-MAN---IRON-LEGION-VS--HYDRA-76288-PL4582",
        "matchConfidence": 100,
        "error": "Produkti nuk u gjet"
      },
      {
        "storeId": "globe",
        "price": null,
        "inStock": null,
        "stockLabel": "E panjohur",
        "productUrl": null,
        "lastChecked": "2026-05-06T09:44:30.369Z",
        "error": "Produkti nuk u gjet"
      },
      {
        "storeId": "albagame",
        "price": null,
        "inStock": null,
        "stockLabel": "E panjohur",
        "productUrl": null,
        "lastChecked": "2026-05-06T09:44:24.694Z",
        "error": "Produkti nuk u gjet"
      }
    ],
    "refreshedAt": "2026-05-06T09:44:30.377Z"
  },
  "albagame-lego-dc-comics-batman-vs-superman-batmobile-76331": {
    "prices": [
      {
        "storeId": "foleja",
        "price": null,
        "inStock": null,
        "stockLabel": "E panjohur",
        "productUrl": null,
        "lastChecked": "2026-05-06T09:44:25.615Z",
        "error": "Produkti nuk u gjet"
      },
      {
        "storeId": "shpresa",
        "price": null,
        "inStock": null,
        "stockLabel": "E panjohur",
        "productUrl": null,
        "lastChecked": "2026-05-06T09:44:30.378Z",
        "error": "Produkti nuk u gjet"
      },
      {
        "storeId": "neptun",
        "price": 2190,
        "inStock": true,
        "stockLabel": "Në gjendje",
        "productUrl": "https://www.neptun.al/categories/Lego-DC-Comics-Batman---Batmobile-vs--Mr--Freeze-S-PL4378",
        "lastChecked": "2026-05-06T09:44:24.352Z",
        "matchedName": "Lego DC Comics Batman & Batmobile vs. Mr. Freeze S",
        "storeProductId": "/categories/Lego-DC-Comics-Batman---Batmobile-vs--Mr--Freeze-S-PL4378",
        "matchConfidence": 100
      },
      {
        "storeId": "globe",
        "price": null,
        "inStock": null,
        "stockLabel": "E panjohur",
        "productUrl": null,
        "lastChecked": "2026-05-06T09:44:27.237Z",
        "error": "Produkti nuk u gjet"
      },
      {
        "storeId": "albagame",
        "price": null,
        "inStock": null,
        "stockLabel": "E panjohur",
        "productUrl": null,
        "lastChecked": "2026-05-06T09:44:24.700Z",
        "error": "Produkti nuk u gjet"
      }
    ],
    "refreshedAt": "2026-05-06T09:44:30.449Z"
  },
  "albagame-lego-city-police-train-heist-set-60508": {
    "prices": [
      {
        "storeId": "foleja",
        "price": null,
        "inStock": null,
        "stockLabel": "E panjohur",
        "productUrl": null,
        "lastChecked": "2026-05-06T09:44:25.792Z",
        "error": "Produkti nuk u gjet"
      },
      {
        "storeId": "shpresa",
        "price": null,
        "inStock": null,
        "stockLabel": "E panjohur",
        "productUrl": null,
        "lastChecked": "2026-05-06T09:44:30.561Z",
        "error": "Produkti nuk u gjet"
      },
      {
        "storeId": "neptun",
        "price": 2190,
        "inStock": true,
        "stockLabel": "Në gjendje",
        "productUrl": "https://www.neptun.al/categories/LEGO-MOBILE-POLICE-DOG-TRAINING-F4-PL4685",
        "lastChecked": "2026-05-06T09:44:24.524Z",
        "matchedName": "LEGO CITY MOBILE POLICE DOG TRAINING 60369",
        "storeProductId": "/categories/LEGO-MOBILE-POLICE-DOG-TRAINING-F4-PL4685",
        "matchConfidence": 100
      },
      {
        "storeId": "globe",
        "price": null,
        "inStock": null,
        "stockLabel": "E panjohur",
        "productUrl": null,
        "lastChecked": "2026-05-06T09:44:30.265Z",
        "error": "Produkti nuk u gjet"
      },
      {
        "storeId": "albagame",
        "price": null,
        "inStock": null,
        "stockLabel": "E panjohur",
        "productUrl": null,
        "lastChecked": "2026-05-06T09:44:24.696Z",
        "error": "Produkti nuk u gjet"
      }
    ],
    "refreshedAt": "2026-05-06T09:44:30.561Z"
  },
  "albagame-lego-pokemon-pikachu-e-poke-ball-72152": {
    "prices": [
      {
        "storeId": "foleja",
        "price": null,
        "inStock": null,
        "stockLabel": "E panjohur",
        "productUrl": null,
        "lastChecked": "2026-05-06T09:44:25.761Z",
        "error": "Produkti nuk u gjet"
      },
      {
        "storeId": "shpresa",
        "price": null,
        "inStock": null,
        "stockLabel": "E panjohur",
        "productUrl": null,
        "lastChecked": "2026-05-06T09:44:30.588Z",
        "error": "Produkti nuk u gjet"
      },
      {
        "storeId": "neptun",
        "price": null,
        "inStock": null,
        "stockLabel": "E panjohur",
        "productUrl": null,
        "lastChecked": "2026-05-06T09:44:24.856Z",
        "error": "Produkti nuk u gjet"
      },
      {
        "storeId": "globe",
        "price": null,
        "inStock": null,
        "stockLabel": "E panjohur",
        "productUrl": null,
        "lastChecked": "2026-05-06T09:44:30.962Z",
        "error": "Produkti nuk u gjet"
      },
      {
        "storeId": "albagame",
        "price": null,
        "inStock": null,
        "stockLabel": "E panjohur",
        "productUrl": null,
        "lastChecked": "2026-05-06T09:44:24.690Z",
        "error": "Produkti nuk u gjet"
      }
    ],
    "refreshedAt": "2026-05-06T09:44:30.969Z"
  },
  "albagame-notebook-k-pop-demon-hunters-a5": {
    "prices": [
      {
        "storeId": "foleja",
        "price": null,
        "inStock": null,
        "stockLabel": "E panjohur",
        "productUrl": null,
        "lastChecked": "2026-05-06T09:44:25.808Z",
        "error": "Produkti nuk u gjet"
      },
      {
        "storeId": "shpresa",
        "price": null,
        "inStock": null,
        "stockLabel": "E panjohur",
        "productUrl": null,
        "lastChecked": "2026-05-06T09:44:30.970Z",
        "error": "Produkti nuk u gjet"
      },
      {
        "storeId": "neptun",
        "price": null,
        "inStock": null,
        "stockLabel": "E panjohur",
        "productUrl": null,
        "lastChecked": "2026-05-06T09:44:24.798Z",
        "error": "Produkti nuk u gjet"
      },
      {
        "storeId": "globe",
        "price": null,
        "inStock": null,
        "stockLabel": "E panjohur",
        "productUrl": null,
        "lastChecked": "2026-05-06T09:44:29.989Z",
        "error": "Produkti nuk u gjet"
      },
      {
        "storeId": "albagame",
        "price": null,
        "inStock": null,
        "stockLabel": "E panjohur",
        "productUrl": null,
        "lastChecked": "2026-05-06T09:44:24.721Z",
        "error": "Produkti nuk u gjet"
      }
    ],
    "refreshedAt": "2026-05-06T09:44:30.970Z"
  },
  "albagame-lego-dc-comics-batman-logo-76330": {
    "prices": [
      {
        "storeId": "foleja",
        "price": null,
        "inStock": null,
        "stockLabel": "E panjohur",
        "productUrl": null,
        "lastChecked": "2026-05-06T09:44:25.574Z",
        "error": "Produkti nuk u gjet"
      },
      {
        "storeId": "shpresa",
        "price": null,
        "inStock": null,
        "stockLabel": "E panjohur",
        "productUrl": null,
        "lastChecked": "2026-05-06T09:44:31.518Z",
        "error": "Produkti nuk u gjet"
      },
      {
        "storeId": "neptun",
        "price": 2190,
        "inStock": true,
        "stockLabel": "Në gjendje",
        "productUrl": "https://www.neptun.al/categories/Lego-DC-Comics-Batman---Batmobile-vs--Mr--Freeze-S-PL4378",
        "lastChecked": "2026-05-06T09:44:24.366Z",
        "matchedName": "Lego DC Comics Batman & Batmobile vs. Mr. Freeze S",
        "storeProductId": "/categories/Lego-DC-Comics-Batman---Batmobile-vs--Mr--Freeze-S-PL4378",
        "matchConfidence": 100
      },
      {
        "storeId": "globe",
        "price": null,
        "inStock": null,
        "stockLabel": "E panjohur",
        "productUrl": null,
        "lastChecked": "2026-05-06T09:44:32.087Z",
        "error": "Produkti nuk u gjet"
      },
      {
        "storeId": "albagame",
        "price": null,
        "inStock": null,
        "stockLabel": "E panjohur",
        "productUrl": null,
        "lastChecked": "2026-05-06T09:44:24.693Z",
        "error": "Produkti nuk u gjet"
      }
    ],
    "refreshedAt": "2026-05-06T09:44:32.096Z"
  },
  "albagame-lego-ninjago-lloyds-mech-15th-anniversary-71860": {
    "prices": [
      {
        "storeId": "foleja",
        "price": null,
        "inStock": null,
        "stockLabel": "E panjohur",
        "productUrl": null,
        "lastChecked": "2026-05-06T09:44:25.681Z",
        "error": "Produkti nuk u gjet"
      },
      {
        "storeId": "shpresa",
        "price": null,
        "inStock": null,
        "stockLabel": "E panjohur",
        "productUrl": null,
        "lastChecked": "2026-05-06T09:44:31.543Z",
        "error": "Produkti nuk u gjet"
      },
      {
        "storeId": "neptun",
        "price": null,
        "inStock": null,
        "stockLabel": "E panjohur",
        "productUrl": null,
        "lastChecked": "2026-05-06T09:44:24.835Z",
        "error": "Produkti nuk u gjet"
      },
      {
        "storeId": "globe",
        "price": null,
        "inStock": null,
        "stockLabel": "E panjohur",
        "productUrl": null,
        "lastChecked": "2026-05-06T09:44:32.960Z",
        "error": "Produkti nuk u gjet"
      },
      {
        "storeId": "albagame",
        "price": null,
        "inStock": null,
        "stockLabel": "E panjohur",
        "productUrl": null,
        "lastChecked": "2026-05-06T09:44:24.692Z",
        "error": "Produkti nuk u gjet"
      }
    ],
    "refreshedAt": "2026-05-06T09:44:32.968Z"
  },
  "albagame-lego-ninjago-jays-dragon-mech-fight-71853": {
    "prices": [
      {
        "storeId": "foleja",
        "price": null,
        "inStock": null,
        "stockLabel": "E panjohur",
        "productUrl": null,
        "lastChecked": "2026-05-06T09:44:25.833Z",
        "error": "Produkti nuk u gjet"
      },
      {
        "storeId": "shpresa",
        "price": null,
        "inStock": null,
        "stockLabel": "E panjohur",
        "productUrl": null,
        "lastChecked": "2026-05-06T09:44:31.919Z",
        "error": "Produkti nuk u gjet"
      },
      {
        "storeId": "neptun",
        "price": null,
        "inStock": null,
        "stockLabel": "E panjohur",
        "productUrl": null,
        "lastChecked": "2026-05-06T09:44:24.881Z",
        "error": "Produkti nuk u gjet"
      },
      {
        "storeId": "globe",
        "price": null,
        "inStock": null,
        "stockLabel": "E panjohur",
        "productUrl": null,
        "lastChecked": "2026-05-06T09:44:33.245Z",
        "error": "Produkti nuk u gjet"
      },
      {
        "storeId": "albagame",
        "price": null,
        "inStock": null,
        "stockLabel": "E panjohur",
        "productUrl": null,
        "lastChecked": "2026-05-06T09:44:24.687Z",
        "error": "Produkti nuk u gjet"
      }
    ],
    "refreshedAt": "2026-05-06T09:44:33.256Z"
  },
  "albagame-lego-pokemon-eevee-72151": {
    "prices": [
      {
        "storeId": "foleja",
        "price": null,
        "inStock": null,
        "stockLabel": "E panjohur",
        "productUrl": null,
        "lastChecked": "2026-05-06T09:44:25.216Z",
        "error": "Produkti nuk u gjet"
      },
      {
        "storeId": "shpresa",
        "price": null,
        "inStock": null,
        "stockLabel": "E panjohur",
        "productUrl": null,
        "lastChecked": "2026-05-06T09:44:25.490Z",
        "error": "Produkti nuk u gjet"
      },
      {
        "storeId": "neptun",
        "price": null,
        "inStock": null,
        "stockLabel": "E panjohur",
        "productUrl": null,
        "lastChecked": "2026-05-06T09:44:24.702Z",
        "error": "Produkti nuk u gjet"
      },
      {
        "storeId": "globe",
        "price": null,
        "inStock": null,
        "stockLabel": "E panjohur",
        "productUrl": null,
        "lastChecked": "2026-05-06T09:44:33.658Z",
        "error": "Produkti nuk u gjet"
      },
      {
        "storeId": "albagame",
        "price": null,
        "inStock": null,
        "stockLabel": "E panjohur",
        "productUrl": null,
        "lastChecked": "2026-05-06T09:44:24.635Z",
        "error": "Produkti nuk u gjet"
      }
    ],
    "refreshedAt": "2026-05-06T09:44:33.659Z"
  },
  "albagame-switch-8-porta-cudy-8x-gigabit-ethernet-rj45-steel-housing-black-gs108": {
    "prices": [
      {
        "storeId": "foleja",
        "price": null,
        "inStock": null,
        "stockLabel": "E panjohur",
        "productUrl": null,
        "lastChecked": "2026-05-06T09:44:34.827Z",
        "error": "Produkti nuk u gjet"
      },
      {
        "storeId": "shpresa",
        "price": null,
        "inStock": null,
        "stockLabel": "E panjohur",
        "productUrl": null,
        "lastChecked": "2026-05-06T09:44:36.024Z",
        "error": "Produkti nuk u gjet"
      },
      {
        "storeId": "neptun",
        "price": null,
        "inStock": null,
        "stockLabel": "E panjohur",
        "productUrl": null,
        "lastChecked": "2026-05-06T09:44:34.330Z",
        "error": "Produkti nuk u gjet"
      },
      {
        "storeId": "globe",
        "price": null,
        "inStock": null,
        "stockLabel": "E panjohur",
        "productUrl": null,
        "lastChecked": "2026-05-06T09:44:35.997Z",
        "error": "Produkti nuk u gjet"
      },
      {
        "storeId": "albagame",
        "price": null,
        "inStock": null,
        "stockLabel": "E panjohur",
        "productUrl": null,
        "lastChecked": "2026-05-06T09:44:34.201Z",
        "error": "Produkti nuk u gjet"
      }
    ],
    "refreshedAt": "2026-05-06T09:44:36.025Z"
  },
  "albagame-adapter-cudy-ac1300-wireless-dual-band-2-4ghz-5ghz-black-wu1300s": {
    "prices": [
      {
        "storeId": "foleja",
        "price": null,
        "inStock": null,
        "stockLabel": "E panjohur",
        "productUrl": null,
        "lastChecked": "2026-05-06T09:44:34.859Z",
        "error": "Produkti nuk u gjet"
      },
      {
        "storeId": "shpresa",
        "price": null,
        "inStock": null,
        "stockLabel": "E panjohur",
        "productUrl": null,
        "lastChecked": "2026-05-06T09:44:36.160Z",
        "error": "Produkti nuk u gjet"
      },
      {
        "storeId": "neptun",
        "price": null,
        "inStock": null,
        "stockLabel": "E panjohur",
        "productUrl": null,
        "lastChecked": "2026-05-06T09:44:34.243Z",
        "error": "Produkti nuk u gjet"
      },
      {
        "storeId": "globe",
        "price": null,
        "inStock": null,
        "stockLabel": "E panjohur",
        "productUrl": null,
        "lastChecked": "2026-05-06T09:44:34.494Z",
        "error": "Produkti nuk u gjet"
      },
      {
        "storeId": "albagame",
        "price": null,
        "inStock": null,
        "stockLabel": "E panjohur",
        "productUrl": null,
        "lastChecked": "2026-05-06T09:44:34.213Z",
        "error": "Produkti nuk u gjet"
      }
    ],
    "refreshedAt": "2026-05-06T09:44:36.161Z"
  },
  "albagame-adapter-cudy-bu530-bluetooth-bt-5-3-usb-a-black-bu530": {
    "prices": [
      {
        "storeId": "foleja",
        "price": 707,
        "inStock": true,
        "stockLabel": "Në gjendje",
        "productUrl": "https://www.foleja.al/ACN-300314739/Adapter-Bluetooth-CUDY-BU530-USB-Type-A-i-zi",
        "lastChecked": "2026-05-06T09:44:35.131Z",
        "matchedName": "Adapter Bluetooth CUDY BU530, USB Type-A, i zi",
        "storeProductId": "/ACN-300314739/Adapter-Bluetooth-CUDY-BU530-USB-Type-A-i-zi",
        "matchConfidence": 100
      },
      {
        "storeId": "shpresa",
        "price": null,
        "inStock": null,
        "stockLabel": "E panjohur",
        "productUrl": null,
        "lastChecked": "2026-05-06T09:44:36.340Z",
        "error": "Produkti nuk u gjet"
      },
      {
        "storeId": "neptun",
        "price": null,
        "inStock": null,
        "stockLabel": "E panjohur",
        "productUrl": null,
        "lastChecked": "2026-05-06T09:44:34.320Z",
        "error": "Produkti nuk u gjet"
      },
      {
        "storeId": "globe",
        "price": null,
        "inStock": null,
        "stockLabel": "E panjohur",
        "productUrl": null,
        "lastChecked": "2026-05-06T09:44:34.343Z",
        "error": "Produkti nuk u gjet"
      },
      {
        "storeId": "albagame",
        "price": null,
        "inStock": null,
        "stockLabel": "E panjohur",
        "productUrl": null,
        "lastChecked": "2026-05-06T09:44:34.216Z",
        "error": "Produkti nuk u gjet"
      }
    ],
    "refreshedAt": "2026-05-06T09:44:36.341Z"
  },
  "albagame-dg-roblox-25-usd-account-us": {
    "prices": [
      {
        "storeId": "foleja",
        "price": null,
        "inStock": null,
        "stockLabel": "E panjohur",
        "productUrl": null,
        "lastChecked": "2026-05-06T09:44:35.031Z",
        "error": "Produkti nuk u gjet"
      },
      {
        "storeId": "shpresa",
        "price": null,
        "inStock": null,
        "stockLabel": "E panjohur",
        "productUrl": null,
        "lastChecked": "2026-05-06T09:44:36.474Z",
        "error": "Produkti nuk u gjet"
      },
      {
        "storeId": "neptun",
        "price": null,
        "inStock": null,
        "stockLabel": "E panjohur",
        "productUrl": null,
        "lastChecked": "2026-05-06T09:44:34.429Z",
        "error": "Produkti nuk u gjet"
      },
      {
        "storeId": "globe",
        "price": null,
        "inStock": null,
        "stockLabel": "E panjohur",
        "productUrl": null,
        "lastChecked": "2026-05-06T09:44:34.499Z",
        "error": "Produkti nuk u gjet"
      },
      {
        "storeId": "albagame",
        "price": null,
        "inStock": null,
        "stockLabel": "E panjohur",
        "productUrl": null,
        "lastChecked": "2026-05-06T09:44:34.246Z",
        "error": "Produkti nuk u gjet"
      }
    ],
    "refreshedAt": "2026-05-06T09:44:36.474Z"
  },
  "albagame-adapter-pcie-tp-link-archer-be9300-wireless-wifi-7-bt-5-4-tbe550e": {
    "prices": [
      {
        "storeId": "foleja",
        "price": null,
        "inStock": null,
        "stockLabel": "Në gjendje",
        "productUrl": "https://www.foleja.al/ICO-200003241/Adapter-Wi-Fi-PCIe-TP-Link-Archer-TXE72E-me-antena-te-jashtme-e-zeze",
        "lastChecked": "2026-05-06T09:44:35.868Z",
        "matchedName": "Adapter Wi‑Fi PCIe, TP-Link Archer TXE72E, me antena të jashtme, e zezë",
        "storeProductId": "/ICO-200003241/Adapter-Wi-Fi-PCIe-TP-Link-Archer-TXE72E-me-antena-te-jashtme-e-zeze",
        "matchConfidence": 100,
        "error": "Produkti nuk u gjet"
      },
      {
        "storeId": "shpresa",
        "price": null,
        "inStock": null,
        "stockLabel": "E panjohur",
        "productUrl": null,
        "lastChecked": "2026-05-06T09:44:36.612Z",
        "error": "Produkti nuk u gjet"
      },
      {
        "storeId": "neptun",
        "price": null,
        "inStock": null,
        "stockLabel": "E panjohur",
        "productUrl": null,
        "lastChecked": "2026-05-06T09:44:34.451Z",
        "error": "Produkti nuk u gjet"
      },
      {
        "storeId": "globe",
        "price": null,
        "inStock": null,
        "stockLabel": "E panjohur",
        "productUrl": null,
        "lastChecked": "2026-05-06T09:44:35.857Z",
        "error": "Produkti nuk u gjet"
      },
      {
        "storeId": "albagame",
        "price": null,
        "inStock": null,
        "stockLabel": "E panjohur",
        "productUrl": null,
        "lastChecked": "2026-05-06T09:44:34.261Z",
        "error": "Produkti nuk u gjet"
      }
    ],
    "refreshedAt": "2026-05-06T09:44:36.613Z"
  },
  "albagame-switch-8-porta-gigabit-tp-link-8x-gigabit-ethernet-rj45-steel-housing-tl-sg108": {
    "prices": [
      {
        "storeId": "foleja",
        "price": null,
        "inStock": null,
        "stockLabel": "Në gjendje",
        "productUrl": "https://www.foleja.al/ALB-200000134/Switch-TP-Link-LS1008G-8-porta-Gigabit-i-zi",
        "lastChecked": "2026-05-06T09:44:35.315Z",
        "matchedName": "Switch TP-Link LS1008G, 8 porta, Gigabit, i zi",
        "storeProductId": "/ALB-200000134/Switch-TP-Link-LS1008G-8-porta-Gigabit-i-zi",
        "matchConfidence": 100,
        "error": "Produkti nuk u gjet"
      },
      {
        "storeId": "shpresa",
        "price": null,
        "inStock": null,
        "stockLabel": "E panjohur",
        "productUrl": null,
        "lastChecked": "2026-05-06T09:44:36.980Z",
        "error": "Produkti nuk u gjet"
      },
      {
        "storeId": "neptun",
        "price": null,
        "inStock": null,
        "stockLabel": "Në gjendje",
        "productUrl": "https://www.neptun.al/categories/SWITCH-TP-LINK-TL-SG1008D-8-PORTA-GIGABIT-SW0037",
        "lastChecked": "2026-05-06T09:44:34.088Z",
        "matchedName": "SWITCH TP-LINK TL-SG1008D 8-PORTA GIGABIT",
        "storeProductId": "/categories/SWITCH-TP-LINK-TL-SG1008D-8-PORTA-GIGABIT-SW0037",
        "matchConfidence": 100,
        "error": "Produkti nuk u gjet"
      },
      {
        "storeId": "globe",
        "price": null,
        "inStock": null,
        "stockLabel": "E panjohur",
        "productUrl": null,
        "lastChecked": "2026-05-06T09:44:35.992Z",
        "error": "Produkti nuk u gjet"
      },
      {
        "storeId": "albagame",
        "price": null,
        "inStock": null,
        "stockLabel": "E panjohur",
        "productUrl": null,
        "lastChecked": "2026-05-06T09:44:34.260Z",
        "error": "Produkti nuk u gjet"
      }
    ],
    "refreshedAt": "2026-05-06T09:44:36.981Z"
  },
  "albagame-charger-24w-baseus-quick-charger-usb-a-white-ccall-bx02": {
    "prices": [
      {
        "storeId": "foleja",
        "price": null,
        "inStock": null,
        "stockLabel": "Në gjendje",
        "productUrl": "https://www.foleja.al/INP-200000260/Karikues-i-shpejte-Baseus-Super-Si-Quick-Charger-1C-TZCCSUP-B01-me-kabllo-USB-C-ne-Lightning-1m-Zi",
        "lastChecked": "2026-05-06T09:44:35.158Z",
        "matchedName": "Karikues i shpejtë Baseus Super Si Quick Charger 1C TZCCSUP-B01 me kabllo USB-C në Lightning 1m, Zi",
        "storeProductId": "/INP-200000260/Karikues-i-shpejte-Baseus-Super-Si-Quick-Charger-1C-TZCCSUP-B01-me-kabllo-USB-C-ne-Lightning-1m-Zi",
        "matchConfidence": 80,
        "error": "Produkti nuk u gjet"
      },
      {
        "storeId": "shpresa",
        "price": null,
        "inStock": null,
        "stockLabel": "E panjohur",
        "productUrl": null,
        "lastChecked": "2026-05-06T09:44:37.697Z",
        "error": "Produkti nuk u gjet"
      },
      {
        "storeId": "neptun",
        "price": null,
        "inStock": null,
        "stockLabel": "E panjohur",
        "productUrl": null,
        "lastChecked": "2026-05-06T09:44:34.370Z",
        "error": "Produkti nuk u gjet"
      },
      {
        "storeId": "globe",
        "price": null,
        "inStock": null,
        "stockLabel": "E panjohur",
        "productUrl": null,
        "lastChecked": "2026-05-06T09:44:34.493Z",
        "error": "Produkti nuk u gjet"
      },
      {
        "storeId": "albagame",
        "price": null,
        "inStock": null,
        "stockLabel": "E panjohur",
        "productUrl": null,
        "lastChecked": "2026-05-06T09:44:34.262Z",
        "error": "Produkti nuk u gjet"
      }
    ],
    "refreshedAt": "2026-05-06T09:44:37.698Z"
  },
  "albagame-ps5-fatal-frame-ii-crimson-butterfly": {
    "prices": [
      {
        "storeId": "foleja",
        "price": null,
        "inStock": null,
        "stockLabel": "E panjohur",
        "productUrl": null,
        "lastChecked": "2026-05-06T09:44:35.192Z",
        "error": "Produkti nuk u gjet"
      },
      {
        "storeId": "shpresa",
        "price": null,
        "inStock": null,
        "stockLabel": "E panjohur",
        "productUrl": null,
        "lastChecked": "2026-05-06T09:44:36.858Z",
        "error": "Produkti nuk u gjet"
      },
      {
        "storeId": "neptun",
        "price": null,
        "inStock": null,
        "stockLabel": "E panjohur",
        "productUrl": null,
        "lastChecked": "2026-05-06T09:44:34.385Z",
        "error": "Produkti nuk u gjet"
      },
      {
        "storeId": "globe",
        "price": null,
        "inStock": null,
        "stockLabel": "E panjohur",
        "productUrl": null,
        "lastChecked": "2026-05-06T09:44:38.591Z",
        "error": "Produkti nuk u gjet"
      },
      {
        "storeId": "albagame",
        "price": null,
        "inStock": null,
        "stockLabel": "E panjohur",
        "productUrl": null,
        "lastChecked": "2026-05-06T09:44:34.254Z",
        "error": "Produkti nuk u gjet"
      }
    ],
    "refreshedAt": "2026-05-06T09:44:38.593Z"
  },
  "albagame-notebook-15-6-lenovo-loq-15irx10-fhd-i5-13450hx-16gb-ram-512gb-ssd-rtx-5050-free-dos-83je007spb-1y": {
    "prices": [
      {
        "storeId": "foleja",
        "price": null,
        "inStock": null,
        "stockLabel": "E panjohur",
        "productUrl": "https://www.foleja.al/KST-200065964/Laptop-Lenovo-LOQ-15IRX10-Core-i5-13450HX-16GB-1TB-SSD-RTX-5060-15.6-FHD-144Hz-gri",
        "lastChecked": "2026-05-06T09:44:35.872Z",
        "matchedName": "Laptop Lenovo LOQ 15IRX10, Core i5-13450HX, 16GB/1TB SSD, RTX 5060, 15.6\" FHD 144Hz, gri",
        "storeProductId": "/KST-200065964/Laptop-Lenovo-LOQ-15IRX10-Core-i5-13450HX-16GB-1TB-SSD-RTX-5060-15.6-FHD-144Hz-gri",
        "matchConfidence": 100,
        "error": "Produkti nuk u gjet"
      },
      {
        "storeId": "shpresa",
        "price": null,
        "inStock": null,
        "stockLabel": "E panjohur",
        "productUrl": null,
        "lastChecked": "2026-05-06T09:44:38.595Z",
        "error": "Produkti nuk u gjet"
      },
      {
        "storeId": "neptun",
        "price": null,
        "inStock": null,
        "stockLabel": "Në gjendje",
        "productUrl": "https://www.neptun.al/categories/LAPTOP-GAMING-LENOVO-LOQ-15IRX10-83JE00XHRM-LP2090",
        "lastChecked": "2026-05-06T09:44:34.073Z",
        "matchedName": "LAPTOP LENOVO GAMING LOQ 15IRX10 83JE00XHRM",
        "storeProductId": "/categories/LAPTOP-GAMING-LENOVO-LOQ-15IRX10-83JE00XHRM-LP2090",
        "matchConfidence": 100,
        "error": "Produkti nuk u gjet"
      },
      {
        "storeId": "globe",
        "price": null,
        "inStock": null,
        "stockLabel": "E panjohur",
        "productUrl": null,
        "lastChecked": "2026-05-06T09:44:34.468Z",
        "error": "Produkti nuk u gjet"
      },
      {
        "storeId": "albagame",
        "price": null,
        "inStock": null,
        "stockLabel": "E panjohur",
        "productUrl": null,
        "lastChecked": "2026-05-06T09:44:34.320Z",
        "error": "Produkti nuk u gjet"
      }
    ],
    "refreshedAt": "2026-05-06T09:44:38.595Z"
  },
  "albagame-notebook-15-6-asus-v16-fhd-core-5-210h-16gb-ram-512gb-ssd-rtx-5060-free-dos-v3607vm-rp015-1y": {
    "prices": [
      {
        "storeId": "foleja",
        "price": null,
        "inStock": null,
        "stockLabel": "E panjohur",
        "productUrl": "https://www.foleja.al/KST-200057470/Monitor-ASUS-TUF-Gaming-VG259QL5A-24.5-inc-FHD-HDMI-DP-i-zi",
        "lastChecked": "2026-05-06T09:44:35.636Z",
        "matchedName": "Monitor ASUS TUF Gaming VG259QL5A, 24.5 inç, FHD, HDMI DP, i zi",
        "storeProductId": "/KST-200057470/Monitor-ASUS-TUF-Gaming-VG259QL5A-24.5-inc-FHD-HDMI-DP-i-zi",
        "matchConfidence": 67,
        "error": "Produkti nuk u gjet"
      },
      {
        "storeId": "shpresa",
        "price": null,
        "inStock": null,
        "stockLabel": "E panjohur",
        "productUrl": null,
        "lastChecked": "2026-05-06T09:44:39.226Z",
        "error": "Produkti nuk u gjet"
      },
      {
        "storeId": "neptun",
        "price": null,
        "inStock": null,
        "stockLabel": "E panjohur",
        "productUrl": null,
        "lastChecked": "2026-05-06T09:44:34.844Z",
        "error": "Produkti nuk u gjet"
      },
      {
        "storeId": "globe",
        "price": null,
        "inStock": null,
        "stockLabel": "E panjohur",
        "productUrl": null,
        "lastChecked": "2026-05-06T09:44:34.493Z",
        "error": "Produkti nuk u gjet"
      },
      {
        "storeId": "albagame",
        "price": null,
        "inStock": null,
        "stockLabel": "E panjohur",
        "productUrl": null,
        "lastChecked": "2026-05-06T09:44:34.346Z",
        "error": "Produkti nuk u gjet"
      }
    ],
    "refreshedAt": "2026-05-06T09:44:39.227Z"
  },
  "albagame-ps5-life-is-strange-reunion": {
    "prices": [
      {
        "storeId": "foleja",
        "price": null,
        "inStock": null,
        "stockLabel": "E panjohur",
        "productUrl": null,
        "lastChecked": "2026-05-06T09:44:35.046Z",
        "error": "Produkti nuk u gjet"
      },
      {
        "storeId": "shpresa",
        "price": null,
        "inStock": null,
        "stockLabel": "E panjohur",
        "productUrl": null,
        "lastChecked": "2026-05-06T09:44:36.621Z",
        "error": "Produkti nuk u gjet"
      },
      {
        "storeId": "neptun",
        "price": null,
        "inStock": null,
        "stockLabel": "E panjohur",
        "productUrl": null,
        "lastChecked": "2026-05-06T09:44:34.345Z",
        "error": "Produkti nuk u gjet"
      },
      {
        "storeId": "globe",
        "price": null,
        "inStock": null,
        "stockLabel": "E panjohur",
        "productUrl": null,
        "lastChecked": "2026-05-06T09:44:41.044Z",
        "error": "Produkti nuk u gjet"
      },
      {
        "storeId": "albagame",
        "price": null,
        "inStock": null,
        "stockLabel": "E panjohur",
        "productUrl": null,
        "lastChecked": "2026-05-06T09:44:34.250Z",
        "error": "Produkti nuk u gjet"
      }
    ],
    "refreshedAt": "2026-05-06T09:44:41.047Z"
  },
  "albagame-switch-2-fatal-frame-ii-crimson-butterfly": {
    "prices": [
      {
        "storeId": "foleja",
        "price": null,
        "inStock": null,
        "stockLabel": "E panjohur",
        "productUrl": null,
        "lastChecked": "2026-05-06T09:44:35.128Z",
        "error": "Produkti nuk u gjet"
      },
      {
        "storeId": "shpresa",
        "price": null,
        "inStock": null,
        "stockLabel": "E panjohur",
        "productUrl": null,
        "lastChecked": "2026-05-06T09:44:36.719Z",
        "error": "Produkti nuk u gjet"
      },
      {
        "storeId": "neptun",
        "price": null,
        "inStock": null,
        "stockLabel": "E panjohur",
        "productUrl": null,
        "lastChecked": "2026-05-06T09:44:34.429Z",
        "error": "Produkti nuk u gjet"
      },
      {
        "storeId": "globe",
        "price": null,
        "inStock": null,
        "stockLabel": "E panjohur",
        "productUrl": null,
        "lastChecked": "2026-05-06T09:44:41.601Z",
        "error": "Produkti nuk u gjet"
      },
      {
        "storeId": "albagame",
        "price": null,
        "inStock": null,
        "stockLabel": "E panjohur",
        "productUrl": null,
        "lastChecked": "2026-05-06T09:44:34.248Z",
        "error": "Produkti nuk u gjet"
      }
    ],
    "refreshedAt": "2026-05-06T09:44:41.605Z"
  },
  "albagame-adapter-cudy-ac1300-wireless-dual-band-2-4ghz-5ghz-black-wu1400": {
    "prices": [
      {
        "storeId": "foleja",
        "price": null,
        "inStock": null,
        "stockLabel": "E panjohur",
        "productUrl": null,
        "lastChecked": "2026-05-06T09:44:41.974Z",
        "error": "Produkti nuk u gjet"
      },
      {
        "storeId": "shpresa",
        "price": null,
        "inStock": null,
        "stockLabel": "E panjohur",
        "productUrl": null,
        "lastChecked": "2026-05-06T09:44:43.066Z",
        "error": "Produkti nuk u gjet"
      },
      {
        "storeId": "neptun",
        "price": null,
        "inStock": null,
        "stockLabel": "E panjohur",
        "productUrl": null,
        "lastChecked": "2026-05-06T09:44:42.028Z",
        "error": "Produkti nuk u gjet"
      },
      {
        "storeId": "globe",
        "price": null,
        "inStock": null,
        "stockLabel": "E panjohur",
        "productUrl": null,
        "lastChecked": "2026-05-06T09:44:41.934Z",
        "error": "Produkti nuk u gjet"
      },
      {
        "storeId": "albagame",
        "price": null,
        "inStock": null,
        "stockLabel": "E panjohur",
        "productUrl": null,
        "lastChecked": "2026-05-06T09:44:42.010Z",
        "error": "Produkti nuk u gjet"
      }
    ],
    "refreshedAt": "2026-05-06T09:44:43.067Z"
  },
  "albagame-switch-5-porta-cudy-5x-gigabit-ethernet-rj45-black-gs105d": {
    "prices": [
      {
        "storeId": "foleja",
        "price": null,
        "inStock": null,
        "stockLabel": "Në gjendje",
        "productUrl": "https://www.foleja.al/ACN-300314413/Switch-rrjeti-Cudy-GS105U-5-porta-Gigabit-Ethernet-i-bardhe",
        "lastChecked": "2026-05-06T09:44:42.899Z",
        "matchedName": "Switch rrjeti Cudy GS105U, 5 porta Gigabit Ethernet, i bardhë",
        "storeProductId": "/ACN-300314413/Switch-rrjeti-Cudy-GS105U-5-porta-Gigabit-Ethernet-i-bardhe",
        "matchConfidence": 100,
        "error": "Produkti nuk u gjet"
      },
      {
        "storeId": "shpresa",
        "price": null,
        "inStock": null,
        "stockLabel": "E panjohur",
        "productUrl": null,
        "lastChecked": "2026-05-06T09:44:43.330Z",
        "error": "Produkti nuk u gjet"
      },
      {
        "storeId": "neptun",
        "price": null,
        "inStock": null,
        "stockLabel": "E panjohur",
        "productUrl": null,
        "lastChecked": "2026-05-06T09:44:42.045Z",
        "error": "Produkti nuk u gjet"
      },
      {
        "storeId": "globe",
        "price": null,
        "inStock": null,
        "stockLabel": "E panjohur",
        "productUrl": null,
        "lastChecked": "2026-05-06T09:44:41.939Z",
        "error": "Produkti nuk u gjet"
      },
      {
        "storeId": "albagame",
        "price": null,
        "inStock": null,
        "stockLabel": "E panjohur",
        "productUrl": null,
        "lastChecked": "2026-05-06T09:44:42.004Z",
        "error": "Produkti nuk u gjet"
      }
    ],
    "refreshedAt": "2026-05-06T09:44:43.331Z"
  },
  "albagame-mousepad-savio-black-edition-precision-control-l-70x30x3-black": {
    "prices": [
      {
        "storeId": "foleja",
        "price": null,
        "inStock": null,
        "stockLabel": "E panjohur",
        "productUrl": null,
        "lastChecked": "2026-05-06T09:44:43.093Z",
        "error": "Produkti nuk u gjet"
      },
      {
        "storeId": "shpresa",
        "price": null,
        "inStock": null,
        "stockLabel": "E panjohur",
        "productUrl": null,
        "lastChecked": "2026-05-06T09:44:43.834Z",
        "error": "Produkti nuk u gjet"
      },
      {
        "storeId": "neptun",
        "price": null,
        "inStock": null,
        "stockLabel": "E panjohur",
        "productUrl": null,
        "lastChecked": "2026-05-06T09:44:42.176Z",
        "error": "Produkti nuk u gjet"
      },
      {
        "storeId": "globe",
        "price": null,
        "inStock": null,
        "stockLabel": "E panjohur",
        "productUrl": null,
        "lastChecked": "2026-05-06T09:44:42.525Z",
        "error": "Produkti nuk u gjet"
      },
      {
        "storeId": "albagame",
        "price": null,
        "inStock": null,
        "stockLabel": "E panjohur",
        "productUrl": null,
        "lastChecked": "2026-05-06T09:44:42.035Z",
        "error": "Produkti nuk u gjet"
      }
    ],
    "refreshedAt": "2026-05-06T09:44:43.835Z"
  },
  "albagame-switch-5-porta-gigabit-mercusys-5x-gigabit-ethernet-rj45-black-ms105g": {
    "prices": [
      {
        "storeId": "foleja",
        "price": null,
        "inStock": null,
        "stockLabel": "Në gjendje",
        "productUrl": "https://www.foleja.al/ACN-300320505/Switch-MERCUSYS-MS105GS-5-porta-Gigabit-zi",
        "lastChecked": "2026-05-06T09:44:42.472Z",
        "matchedName": "Switch MERCUSYS MS105GS, 5 porta Gigabit, zi",
        "storeProductId": "/ACN-300320505/Switch-MERCUSYS-MS105GS-5-porta-Gigabit-zi",
        "matchConfidence": 100,
        "error": "Produkti nuk u gjet"
      },
      {
        "storeId": "shpresa",
        "price": null,
        "inStock": null,
        "stockLabel": "E panjohur",
        "productUrl": null,
        "lastChecked": "2026-05-06T09:44:43.952Z",
        "error": "Produkti nuk u gjet"
      },
      {
        "storeId": "neptun",
        "price": null,
        "inStock": null,
        "stockLabel": "Në gjendje",
        "productUrl": "https://www.neptun.al/categories/SWITCH-TP-LINK-TL-SG1005D-5-PORTA-GIGABIT-PC0895",
        "lastChecked": "2026-05-06T09:44:41.888Z",
        "matchedName": "SWITCH TP-LINK TL-SG1005D 5-PORTA GIGABIT",
        "storeProductId": "/categories/SWITCH-TP-LINK-TL-SG1005D-5-PORTA-GIGABIT-PC0895",
        "matchConfidence": 100,
        "error": "Produkti nuk u gjet"
      },
      {
        "storeId": "globe",
        "price": null,
        "inStock": null,
        "stockLabel": "E panjohur",
        "productUrl": null,
        "lastChecked": "2026-05-06T09:44:42.115Z",
        "error": "Produkti nuk u gjet"
      },
      {
        "storeId": "albagame",
        "price": null,
        "inStock": null,
        "stockLabel": "E panjohur",
        "productUrl": null,
        "lastChecked": "2026-05-06T09:44:42.030Z",
        "error": "Produkti nuk u gjet"
      }
    ],
    "refreshedAt": "2026-05-06T09:44:43.954Z"
  },
  "albagame-switch-5-porta-gigabit-tp-link-5x-gigabit-ethernet-rj45-steel-housing-tl-ls105g": {
    "prices": [
      {
        "storeId": "foleja",
        "price": null,
        "inStock": null,
        "stockLabel": "Në gjendje",
        "productUrl": "https://www.foleja.al/ACN-300014476/Switch-i-Mencur-TP-Link-me-5-Porta-Gigabit",
        "lastChecked": "2026-05-06T09:44:43.072Z",
        "matchedName": "Switch i Mençur TP-Link me 5 Porta Gigabit",
        "storeProductId": "/ACN-300014476/Switch-i-Mencur-TP-Link-me-5-Porta-Gigabit",
        "matchConfidence": 100,
        "error": "Produkti nuk u gjet"
      },
      {
        "storeId": "shpresa",
        "price": null,
        "inStock": null,
        "stockLabel": "E panjohur",
        "productUrl": null,
        "lastChecked": "2026-05-06T09:44:44.113Z",
        "error": "Produkti nuk u gjet"
      },
      {
        "storeId": "neptun",
        "price": null,
        "inStock": null,
        "stockLabel": "Në gjendje",
        "productUrl": "https://www.neptun.al/categories/SWITCH-TP-LINK-TL-SG1005D-5-PORTA-GIGABIT-PC0895",
        "lastChecked": "2026-05-06T09:44:41.885Z",
        "matchedName": "SWITCH TP-LINK TL-SG1005D 5-PORTA GIGABIT",
        "storeProductId": "/categories/SWITCH-TP-LINK-TL-SG1005D-5-PORTA-GIGABIT-PC0895",
        "matchConfidence": 100,
        "error": "Produkti nuk u gjet"
      },
      {
        "storeId": "globe",
        "price": null,
        "inStock": null,
        "stockLabel": "E panjohur",
        "productUrl": null,
        "lastChecked": "2026-05-06T09:44:41.979Z",
        "error": "Produkti nuk u gjet"
      },
      {
        "storeId": "albagame",
        "price": null,
        "inStock": null,
        "stockLabel": "E panjohur",
        "productUrl": null,
        "lastChecked": "2026-05-06T09:44:42.031Z",
        "error": "Produkti nuk u gjet"
      }
    ],
    "refreshedAt": "2026-05-06T09:44:44.114Z"
  },
  "albagame-cable-0-5m-usb-c-baseus-cafule-usb-a-to-usb-c-up-to-60w-fast-charging-red-catklf-a09": {
    "prices": [
      {
        "storeId": "foleja",
        "price": null,
        "inStock": null,
        "stockLabel": "E panjohur",
        "productUrl": null,
        "lastChecked": "2026-05-06T09:44:42.725Z",
        "error": "Produkti nuk u gjet"
      },
      {
        "storeId": "shpresa",
        "price": null,
        "inStock": null,
        "stockLabel": "E panjohur",
        "productUrl": null,
        "lastChecked": "2026-05-06T09:44:44.250Z",
        "error": "Produkti nuk u gjet"
      },
      {
        "storeId": "neptun",
        "price": null,
        "inStock": null,
        "stockLabel": "E panjohur",
        "productUrl": null,
        "lastChecked": "2026-05-06T09:44:42.155Z",
        "error": "Produkti nuk u gjet"
      },
      {
        "storeId": "globe",
        "price": null,
        "inStock": null,
        "stockLabel": "E panjohur",
        "productUrl": null,
        "lastChecked": "2026-05-06T09:44:42.525Z",
        "error": "Produkti nuk u gjet"
      },
      {
        "storeId": "albagame",
        "price": null,
        "inStock": null,
        "stockLabel": "E panjohur",
        "productUrl": null,
        "lastChecked": "2026-05-06T09:44:42.034Z",
        "error": "Produkti nuk u gjet"
      }
    ],
    "refreshedAt": "2026-05-06T09:44:44.252Z"
  },
  "albagame-cable-2m-usb-c-baseus-dura-usb-a-to-usb-c-up-to-60w-fast-charging-black-p10377802u01-03": {
    "prices": [
      {
        "storeId": "foleja",
        "price": null,
        "inStock": null,
        "stockLabel": "E panjohur",
        "productUrl": null,
        "lastChecked": "2026-05-06T09:44:43.117Z",
        "error": "Produkti nuk u gjet"
      },
      {
        "storeId": "shpresa",
        "price": null,
        "inStock": null,
        "stockLabel": "E panjohur",
        "productUrl": null,
        "lastChecked": "2026-05-06T09:44:44.391Z",
        "error": "Produkti nuk u gjet"
      },
      {
        "storeId": "neptun",
        "price": null,
        "inStock": null,
        "stockLabel": "E panjohur",
        "productUrl": null,
        "lastChecked": "2026-05-06T09:44:42.130Z",
        "error": "Produkti nuk u gjet"
      },
      {
        "storeId": "globe",
        "price": null,
        "inStock": null,
        "stockLabel": "E panjohur",
        "productUrl": null,
        "lastChecked": "2026-05-06T09:44:42.497Z",
        "error": "Produkti nuk u gjet"
      },
      {
        "storeId": "albagame",
        "price": null,
        "inStock": null,
        "stockLabel": "E panjohur",
        "productUrl": null,
        "lastChecked": "2026-05-06T09:44:42.079Z",
        "error": "Produkti nuk u gjet"
      }
    ],
    "refreshedAt": "2026-05-06T09:44:44.392Z"
  },
  "albagame-switch-8-porta-gigabit-mercusys-8x-gigabit-ethernet-rj45-black-ms108g": {
    "prices": [
      {
        "storeId": "foleja",
        "price": null,
        "inStock": null,
        "stockLabel": "Në gjendje",
        "productUrl": "https://www.foleja.al/ALB-200000134/Switch-TP-Link-LS1008G-8-porta-Gigabit-i-zi",
        "lastChecked": "2026-05-06T09:44:43.367Z",
        "matchedName": "Switch TP-Link LS1008G, 8 porta, Gigabit, i zi",
        "storeProductId": "/ALB-200000134/Switch-TP-Link-LS1008G-8-porta-Gigabit-i-zi",
        "matchConfidence": 100,
        "error": "Produkti nuk u gjet"
      },
      {
        "storeId": "shpresa",
        "price": null,
        "inStock": null,
        "stockLabel": "E panjohur",
        "productUrl": null,
        "lastChecked": "2026-05-06T09:44:44.620Z",
        "error": "Produkti nuk u gjet"
      },
      {
        "storeId": "neptun",
        "price": null,
        "inStock": null,
        "stockLabel": "Në gjendje",
        "productUrl": "https://www.neptun.al/categories/SWITCH-TP-LINK-TL-SG1008D-8-PORTA-GIGABIT-SW0037",
        "lastChecked": "2026-05-06T09:44:41.893Z",
        "matchedName": "SWITCH TP-LINK TL-SG1008D 8-PORTA GIGABIT",
        "storeProductId": "/categories/SWITCH-TP-LINK-TL-SG1008D-8-PORTA-GIGABIT-SW0037",
        "matchConfidence": 100,
        "error": "Produkti nuk u gjet"
      },
      {
        "storeId": "globe",
        "price": null,
        "inStock": null,
        "stockLabel": "E panjohur",
        "productUrl": null,
        "lastChecked": "2026-05-06T09:44:42.109Z",
        "error": "Produkti nuk u gjet"
      },
      {
        "storeId": "albagame",
        "price": null,
        "inStock": null,
        "stockLabel": "E panjohur",
        "productUrl": null,
        "lastChecked": "2026-05-06T09:44:42.044Z",
        "error": "Produkti nuk u gjet"
      }
    ],
    "refreshedAt": "2026-05-06T09:44:44.621Z"
  }
}